[
  {
    "name": "稟",
    "message": "「おはようございます。さすがに寝不足ですねぇ」"
  },
  {
    "name": "直哉",
    "message": "「ああ、寝不足だ……」"
  },
  {
    "name": "稟",
    "message": "「夜空が明るくなったので、急いで寝たぐらいですもんね」"
  },
  {
    "name": "直哉",
    "message": "「ああ……」"
  },
  {
    "message": "俺はその後もあまり寝られなかったが……。"
  },
  {
    "message": "くそ……それにしても朝立ちがきつい……。\r\n稟がいるからオナニーも出来ない。"
  },
  {
    "message": "あんないろいろな事があったあげく、一晩そのまま一つの布団で寝たんだ。\r\nもう、これが朝立ちなのか本立ちなのかさっぱり分からないが、どうでもいいから一発でも抜かないと死んでしまいそうだ。"
  },
  {
    "name": "稟",
    "message": "「ふぁぁあ……眠い。ご飯作りますね」"
  },
  {
    "name": "直哉",
    "message": "「あ、ああ……」"
  },
  {
    "name": "稟",
    "message": "「～♪」"
  },
  {
    "message": "先に起きた稟が俺が起きたのを確認すると、当たり前の様にキッチンへと入っていった。"
  },
  {
    "message": "俺はそんな稟を見送った。"
  },
  {
    "name": "直哉",
    "message": "「……」"
  },
  {
    "name": "直哉",
    "message": "「ふむ……」"
  },
  {
    "message": "リビングからはキッチンが見渡せる。\r\n当然、稟が料理している姿も見る事が出来る。"
  },
  {
    "name": "直哉",
    "message": "「……」"
  },
  {
    "message": "俺は洗面台に向かう。"
  },
  {
    "message": "顔でも真水で洗えば、少しは落ち着くであろう。"
  },
  {
    "message": "おれは洗面器であるものを見つける。"
  },
  {
    "name": "直哉",
    "message": "「これって……」"
  },
  {
    "message": "歯ブラシを手にしようとすると、昨日寝支度する前に、稟と一緒にコンビニで買った歯ブラシセットが置いてある。"
  },
  {
    "message": "色はピンク色。\r\n今までこの家には無い色だ……。"
  },
  {
    "message": "そんな歯ブラシが俺の歯ブラシと並んでいる。"
  },
  {
    "name": "直哉",
    "message": "「なんだ……この幸福感……」"
  },
  {
    "message": "リビングに戻ると、何もする事もなく俺は食卓に座る。"
  },
  {
    "name": "直哉",
    "message": "「なんか手伝おうか？」"
  },
  {
    "name": "稟",
    "message": "「いいですよ。もう少し待ってくださいねー」"
  },
  {
    "name": "直哉",
    "message": "「そうか……」"
  },
  {
    "message": "俺はリビングの机に座るが、何もする事がない。"
  },
  {
    "name": "直哉",
    "message": "「……」"
  },
  {
    "name": "直哉",
    "message": "「本当に、何かしなくていいのか？」"
  },
  {
    "name": "稟",
    "message": "「当たり前ですよ。もうだいたい終わりましたから、あ、なおくんって朝のコーヒー飲みますか？」"
  },
  {
    "name": "直哉",
    "message": "「ああ、そうだな。出来たらブラックで頼む」"
  },
  {
    "name": "稟",
    "message": "「はい、かしこまりました」"
  },
  {
    "message": "俺は手持無沙汰から、意味も無くテレビをつける。\r\n朝のニュース番組がやっているが、あまり集中して見られるものじゃない。"
  },
  {
    "name": "稟",
    "message": "「前ちょっといいですか？」"
  },
  {
    "name": "直哉",
    "message": "「あ、ああ……」"
  },
  {
    "message": "食卓に料理が並んでいく。"
  },
  {
    "name": "直哉",
    "message": "「うまそうだな」"
  },
  {
    "name": "稟",
    "message": "「ごめんね。昨日コンビニで買えるものでしか料理出来なかったから、あまり大層なものが作れなくて……」"
  },
  {
    "name": "直哉",
    "message": "「いやいや、十分だ……」"
  },
  {
    "name": "稟",
    "message": "「なおくんって好き嫌いありませんでしたよね？　あとアレルギーとかは？」"
  },
  {
    "name": "直哉",
    "message": "「大丈夫だ。何でも食える」"
  },
  {
    "name": "稟",
    "message": "「そうですか、良かった」"
  },
  {
    "message": "献立は、わかめと豆腐の味噌汁。"
  },
  {
    "message": "納豆。"
  },
  {
    "message": "オムレツ。"
  },
  {
    "message": "大根の梅干しソースのサラダ。"
  },
  {
    "message": "決して、豪勢な料理ではない。"
  },
  {
    "message": "だが、何だろうか。このえも言われぬ幸福感は……。"
  },
  {
    "name": "稟",
    "message": "「はい、コーヒーです。\r\nすみません、メニューが和洋折衷で……」"
  },
  {
    "name": "直哉",
    "message": "「いやいや、全然かまわない」"
  },
  {
    "name": "稟",
    "message": "「それでは食べましょうかね。いただきまーす」"
  },
  {
    "name": "直哉",
    "message": "「頂きます」"
  },
  {
    "message": "俺は味噌汁を一口すする。"
  },
  {
    "message": "味は粉末状のだしの味では無い。\r\nこれは煮干しからだしをとったものだ。"
  },
  {
    "name": "直哉",
    "message": "「うまいな、ちゃんとだしが取れている」"
  },
  {
    "name": "稟",
    "message": "「なおくんの家って赤だしなのですね」"
  },
  {
    "name": "直哉",
    "message": "「ああ、赤だしは好きだ」"
  },
  {
    "name": "稟",
    "message": "「めずらしいですね。でも赤だしって鰹だしの方が合いませんか？」"
  },
  {
    "name": "直哉",
    "message": "「まぁ、そうなんだが、煮干しの方が値段安いだろ」"
  },
  {
    "name": "稟",
    "message": "「そうですね。本当にその辺りのなおくんの生活力はすごいんですね」"
  },
  {
    "name": "直哉",
    "message": "「何が？」"
  },
  {
    "name": "稟",
    "message": "「いいえ、値段を気にして料理する人なんて、なおくんの年齢でまずいないだろうなぁ……って」"
  },
  {
    "name": "直哉",
    "message": "「金がない一人暮らしだったらそんなもんだろ。ただ俺の場合はそんじょそこらの一人暮らしはじめたての大学生とは、比較にならないぐらい長いってだけだ」"
  },
  {
    "name": "稟",
    "message": "「うん、そう言われてみればそうかも」"
  },
  {
    "name": "直哉",
    "message": "「あと、母親が金に厳しい人でな。まぁ、その影響はあると思う」"
  },
  {
    "name": "稟",
    "message": "「お金って基本的にどうしてるのですか？」"
  },
  {
    "name": "直哉",
    "message": "「親父が母親に送金してた貯金を切り崩している。まぁ、就職まで考えれば、そこまで切り詰めなくても良いだけの蓄えはあるのだが……」"
  },
  {
    "name": "稟",
    "message": "「なるほど、その辺りはお母さんの教育の賜物なんだ」"
  },
  {
    "name": "直哉",
    "message": "「そうだな。倹約は趣味みたいなもんかもしれん。\r\nまぁ、鳥谷にしょせん趣味の範囲だと揶揄される事もあるぐらいだからな」"
  },
  {
    "name": "稟",
    "message": "「まこちゃんは生活本当に大変みたいだね」"
  },
  {
    "name": "直哉",
    "message": "「親と喧嘩してるらしくて、学費も全部自分で稼いでるらしい。勉強も良くやってるし、あいつはいつ寝てるんだろうな」"
  },
  {
    "name": "稟",
    "message": "「食事も結構抜いてしまうみたいですしね」"
  },
  {
    "name": "直哉",
    "message": "「とは言っても、飯とかやると、やれ、貸しだ、借りだ、とうるさい」"
  },
  {
    "name": "稟",
    "message": "「はい、そうですね。それは私も経験済みです」"
  },
  {
    "name": "直哉",
    "message": "「まぁ、あいつはあいつでいろいろあるんだろ……。\r\nあの校長の娘だって話だし」"
  },
  {
    "name": "稟",
    "message": "「校長さん良い人そうですね。美人だし」"
  },
  {
    "name": "直哉",
    "message": "「美人？　ババァだろ？」"
  },
  {
    "name": "稟",
    "message": "「いいえ、年の割には美人です。だいたいそういう言い方は失礼だよ、なおくん」"
  },
  {
    "name": "直哉",
    "message": "「まぁ、そうかもしれないが……」"
  },
  {
    "name": "稟",
    "message": "「あんな風に綺麗に歳を取りたいなぁ……」"
  },
  {
    "name": "直哉",
    "message": "「あんな風に綺麗にか……」"
  },
  {
    "message": "稟のお母さんは綺麗な人だった。"
  },
  {
    "message": "だからお前だって十分、綺麗に歳を取る事ができるさ……。"
  },
  {
    "message": "とは言えない。"
  },
  {
    "message": "まぁ、気恥ずかしいというのもあるが、稟にはこの手の話は御法度なのだ。"
  },
  {
    "message": "俺は稟を見つめる。"
  },
  {
    "message": "歳を取った稟か……。"
  },
  {
    "message": "稟と一緒になれば、ずっと二人でこんな時間を過ごせるのか……。"
  },
  {
    "message": "朝起きて、稟が料理を作ってくれて、食卓を共に囲んでいる。"
  },
  {
    "message": "何とも言えない充足感。"
  },
  {
    "message": "料理は自分で作るものという意識しかない俺には、誰かが料理をしてくれて、ただ待つという、このあたりがなんともいえず心地よかった。"
  },
  {
    "message": "特に、朝のひとときを二人で、というのが何とも言えない。"
  },
  {
    "name": "稟",
    "message": "「ん？　どうしましたか？　そんな顔で私を見て？」"
  },
  {
    "name": "直哉",
    "message": "「っ！？」"
  },
  {
    "name": "直哉",
    "message": "「ど、どんな顔してた？」"
  },
  {
    "name": "稟",
    "message": "「なんだろ、笑顔とも違う……何かをかみしめている様な……」"
  },
  {
    "message": "まんまだな。おい。"
  },
  {
    "name": "直哉",
    "message": "「ま、まぁ、かみしめていたからな……仕方がない」"
  },
  {
    "name": "稟",
    "message": "「何をかみしめていたのですか？」"
  },
  {
    "name": "直哉",
    "message": "「それは、なんだ、その……幸せだなぁ……って、\r\n稟みたいな可愛い彼女が出来て、朝にその……料理作ってくれて……」"
  },
  {
    "name": "稟",
    "message": "「～～っ」"
  },
  {
    "message": "今まで普通にしゃべっていた稟が突然俯く。\r\nそしてか細い声で……、"
  },
  {
    "name": "稟",
    "message": "「そ、それは光栄です……」"
  },
  {
    "name": "稟",
    "message": "「ひ、一晩泊めて頂いてずっと一緒にいられたわけですし……彼女にしていただいたばかりなのですけど……」"
  },
  {
    "name": "直哉",
    "message": "「いやいや、あれは俺が悪いから、泊めるも何も……」"
  },
  {
    "name": "稟",
    "message": "「はい……なんか昨日は大変でした。\r\n私のミスではあるのですが……パンツをはいてない姿を二度も見られましたし……」"
  },
  {
    "name": "直哉",
    "message": "「っ」"
  },
  {
    "name": "稟",
    "message": "「ど、どうしましたか？」"
  },
  {
    "name": "直哉",
    "message": "「あ、いや……なんだ……そのな……」"
  },
  {
    "name": "稟",
    "message": "「はい……」"
  },
  {
    "message": "朝起きた後に、稟よりも後にソファから出てきたのには理由がある。"
  },
  {
    "message": "まぁ、当然と言えば当然すぎる理由。"
  },
  {
    "message": "男なら分かるだろうが、朝というのはどうあっても下半身的に元気になってしまうものだ。"
  },
  {
    "message": "ましてや、昨日の今朝である。"
  },
  {
    "message": "まったく収まる様子などなかったので、真水で顔を洗った。"
  },
  {
    "message": "それでなんとか収まった様なので、リビングで平常を振る舞っているにすぎない……。"
  },
  {
    "name": "直哉",
    "message": "「え、えっとな……あの、なんというか……その……」"
  },
  {
    "message": "なので、“昨日の事”など言われたら、俺の股間はすぐに臨戦態勢となった。"
  },
  {
    "name": "稟",
    "message": "「なんで突然テーブルの下に手を？　ご飯食べられないじゃないですか」"
  },
  {
    "name": "直哉",
    "message": "「あ、いや、なんと言うか、なんと言うだろう……」"
  },
  {
    "name": "稟",
    "message": "「？　ん？　どうしたんですか？　何か隠してるのでしょうか？」"
  },
  {
    "message": "稟はテーブルの下を覗く。"
  },
  {
    "name": "稟",
    "message": "「……」"
  },
  {
    "name": "直哉",
    "message": "「……」"
  },
  {
    "name": "稟",
    "message": "「！？」"
  },
  {
    "name": "稟",
    "message": "「え？　えっと……もしかして……」"
  },
  {
    "name": "直哉",
    "message": "「はい、そのもしかしてです」"
  },
  {
    "name": "稟",
    "message": "「あ、あの……朝になると立つというやつでしょうか？」"
  },
  {
    "name": "直哉",
    "message": "「いや、そうとも言えない……。昨日の稟を思い出したら、こうなったから……」"
  },
  {
    "name": "稟",
    "message": "「き、昨日の私って……」"
  },
  {
    "name": "直哉",
    "message": "「の、ノーパンの稟を……」"
  },
  {
    "name": "稟",
    "message": "「～～」"
  },
  {
    "name": "直哉",
    "message": "「す、すまない……」"
  },
  {
    "name": "稟",
    "message": "「え、えっと……少しお聞きしたいのですが……」"
  },
  {
    "name": "直哉",
    "message": "「なんだ？」"
  },
  {
    "name": "稟",
    "message": "「それって、収まるものなのですか？」"
  },
  {
    "name": "直哉",
    "message": "「まぁ、いつもなら気合いで収まる事もあるのだが……」"
  },
  {
    "name": "直哉",
    "message": "「とりあえず一回でも抜いてしまえばどうにかはなると思うので……」"
  },
  {
    "name": "稟",
    "message": "「ぬ、抜く！？」"
  },
  {
    "name": "直哉",
    "message": "「あ、いや、気にしないでくれ。抜くとかじゃなくて、と、トイレだ」"
  },
  {
    "name": "稟",
    "message": "「っ」"
  },
  {
    "name": "直哉",
    "message": "「！？」"
  },
  {
    "message": "席を立とうとすると、稟に腕を捕まれる。"
  },
  {
    "name": "稟",
    "message": "「じ、自分でするって……事でしょうか？」"
  },
  {
    "name": "直哉",
    "message": "「あ、いや、本当にトイレだよ。お、おしっこ？」"
  },
  {
    "name": "稟",
    "message": "「嘘です」"
  },
  {
    "name": "直哉",
    "message": "「い、いや嘘じゃないから……」"
  },
  {
    "name": "稟",
    "message": "「どちらにしても、そんな状態でおしっこが出来るとは思えません。\r\nえっと、なんて言うか、その……それが上向いてます……」"
  },
  {
    "name": "直哉",
    "message": "「い、いや、それはそうなんだが……何とか出来るから」"
  },
  {
    "name": "稟",
    "message": "「何とかってどうするのですか？　そのままだと上に向かっておしっこが出そうですよ」"
  },
  {
    "name": "直哉",
    "message": "「え、えっと、逆立ちすると大丈夫？」"
  },
  {
    "name": "稟",
    "message": "「そんなの不可能ですよね」"
  },
  {
    "name": "直哉",
    "message": "「そ、その前に抜けば収まるし」"
  },
  {
    "name": "稟",
    "message": "「やっぱり、一人でする気だったのですよね」"
  },
  {
    "name": "直哉",
    "message": "「あっ……、えっと……」"
  },
  {
    "message": "言いよどむ俺の手を稟が握る。"
  },
  {
    "name": "稟",
    "message": "「なら、こ、ここで……」"
  },
  {
    "name": "稟",
    "message": "「ここで……出してみるというのは、ダメでしょうか？」"
  },
  {
    "name": "直哉",
    "message": "「なんでそうなるんだ」"
  },
  {
    "name": "稟",
    "message": "「だって、トイレに２人で入るのはおかしいですし」"
  },
  {
    "name": "直哉",
    "message": "「は？」"
  },
  {
    "name": "稟",
    "message": "「私がお手伝いするなら、ここのほうが広いかなって」"
  },
  {
    "name": "直哉",
    "message": "「なんで稟が手伝う話になるんだ！？」"
  },
  {
    "name": "稟",
    "message": "「だって、それ…………私のせい、なんですよね？」"
  },
  {
    "name": "直哉",
    "message": "「せいっていうか、おかげっていうか……微妙なところだが」"
  },
  {
    "name": "稟",
    "message": "「だったら、私がやりますよ」"
  },
  {
    "name": "直哉",
    "message": "「なんでやねん」"
  },
  {
    "message": "俺はやや、あきれ顔で言う。"
  },
  {
    "name": "直哉",
    "message": "「あのな、稟、誰かのせいとかそういう問題じゃないんだよ。\r\nそんな事で、お前が責任とか感じるのは困る」"
  },
  {
    "name": "直哉",
    "message": "「大丈夫だから、これは自分で何とかするよ」"
  },
  {
    "name": "直哉",
    "message": "「ひっ」"
  },
  {
    "message": "亀頭に手の感触。"
  },
  {
    "message": "俺は思わず声を出してしまう。"
  },
  {
    "name": "稟",
    "message": "「だめだな。私……」"
  },
  {
    "name": "直哉",
    "message": "「な、何が？」"
  },
  {
    "name": "稟",
    "message": "「あのね。なおくん」"
  },
  {
    "name": "直哉",
    "message": "「なに？」"
  },
  {
    "name": "稟",
    "message": "「責任とか感じてじゃないんだよ」"
  },
  {
    "name": "直哉",
    "message": "「え？　ど、どういう事？」"
  },
  {
    "name": "稟",
    "message": "「あ、あのね。なおくん……、単に私がね。その……お手伝いしたいの。\r\nわ、わたしが単にやりたいだけなんだよ」"
  },
  {
    "name": "稟",
    "message": "「だ、だから、もしなおくんが嫌だったらやめるよ。\r\nごめん……なんか浮き足立ってたかも……」"
  },
  {
    "message": "膨らんだズボンの前で、\r\n思いつめたような顔の稟が俺を見上げてくる。"
  },
  {
    "name": "稟",
    "message": "「やっぱり、私はヘンタイさんだね」"
  },
  {
    "name": "直哉",
    "message": "「…………」"
  },
  {
    "name": "直哉",
    "message": "「嫌なわけが無いだろ？」"
  },
  {
    "name": "稟",
    "message": "「え？」"
  },
  {
    "name": "直哉",
    "message": "「今も、お前の手が先に触れて……とても気持ち良かった」"
  },
  {
    "name": "稟",
    "message": "「って、あ、ごめんなさいっっ」"
  },
  {
    "message": "稟は慌てて手を離す。"
  },
  {
    "name": "直哉",
    "message": "「なんだよ。わざとじゃなかったのかよ」"
  },
  {
    "name": "稟",
    "message": "「ご、ごめん、自分的にはなおくんのお腹あたりを触ったつもりだった……」"
  },
  {
    "name": "直哉",
    "message": "「ったく……だったら責任とれ」"
  },
  {
    "name": "稟",
    "message": "「責任？」"
  },
  {
    "name": "直哉",
    "message": "「なんだ、その……手がふれて気持ち良すぎた……。\r\nそうやって離されると、なんだか落ち着かない」"
  },
  {
    "name": "稟",
    "message": "「え？　は、はいっ」"
  },
  {
    "name": "稟",
    "message": "「あ……っ！」"
  },
  {
    "message": "柔らかい圧迫をふたたび股間に感じた。"
  },
  {
    "name": "稟",
    "message": "「……………………」"
  },
  {
    "name": "稟",
    "message": "「……ごくっ！」"
  },
  {
    "name": "直哉",
    "message": "「すごい間だな……」"
  },
  {
    "name": "稟",
    "message": "「えっと、凄さが脳に伝わるまでの時間……かな？」"
  },
  {
    "name": "直哉",
    "message": "「何がすごいんだよ」"
  },
  {
    "name": "稟",
    "message": "「え、えっと……なにが、と言われると説明に困ります。\r\nでも、本当にこんなになるんだね。\r\nエッチな漫画と同じだったからびっくりしたよ」"
  },
  {
    "name": "直哉",
    "message": "「エロ漫画基準なのかよ」"
  },
  {
    "name": "稟",
    "message": "「だって、それでしか知識がないんだもん。\r\nあ、でも、漫画だって分かる事だって沢山ありますよ。\r\nこんなに張り詰めていたら、簡単には収まらないんですよね」"
  },
  {
    "name": "直哉",
    "message": "「ああ、そうだな。\r\nだからって無理する事はないぞ……」"
  },
  {
    "name": "稟",
    "message": "「無理とかありませんよ。\r\nだって私が好きでやるのですから」"
  },
  {
    "name": "直哉",
    "message": "「本当かよ」"
  },
  {
    "name": "稟",
    "message": "「そりゃ、もちろんですよ。だって、私はなおくんの身体触るの好きですもの……、好きすぎてこの前怒られたじゃないですか」"
  },
  {
    "name": "直哉",
    "message": "「ああ、絵を教えてる時か……あれは教えてる時だったから……」"
  },
  {
    "name": "直哉",
    "message": "「それに筋肉を触るのと、そこを触るのじゃ、全然違う」"
  },
  {
    "name": "稟",
    "message": "「はい、全然違います。より刺激的ですもの……」"
  },
  {
    "name": "直哉",
    "message": "「稟……」"
  },
  {
    "name": "稟",
    "message": "「なおくんが『ダメ』って言ったら、すぐにやめますから、だから私に触らせてくれませんか？」"
  },
  {
    "name": "稟",
    "message": "「私は、なおくんの身体を隅々まで触ってみたいです……」"
  },
  {
    "message": "こう言われて、断る事なんて出来るわけがない……。\r\n俺は小さく頷いた。"
  },
  {
    "name": "稟",
    "message": "「わぁ、硬い……」"
  },
  {
    "name": "稟",
    "message": "「こんなに硬くなるんですね……はぁ、はぁ……はぁぁ」"
  },
  {
    "message": "勃起に触れることへのためらいはないように、息を荒げて丹念に触ってくる。"
  },
  {
    "name": "稟",
    "message": "「はぁ、はぁぁ……ふー……ふぅぅ……すごい、本当にこんな硬くなるんだ」"
  },
  {
    "name": "直哉",
    "message": "「なんだよ。それって漫画からの感想か」"
  },
  {
    "name": "稟",
    "message": "「そ、そうですねぇ。あと想像もあったかなぁ」"
  },
  {
    "name": "直哉",
    "message": "「想像？」"
  },
  {
    "name": "稟",
    "message": "「うん、エッチな漫画ってなおくんと探したじゃないですか、やっぱり想像してしまいますよね」"
  },
  {
    "name": "直哉",
    "message": "「何を？」"
  },
  {
    "name": "稟",
    "message": "「なおくんと関連づけてですよ。なおくんのもこんな感じになるのかなぁ……って思いながらエッチな漫画読んでました」"
  },
  {
    "name": "直哉",
    "message": "「そうなのか……」"
  },
  {
    "name": "稟",
    "message": "「うん、やっぱり、なおくんと一緒に見つけて、そして読んだって事が強烈な原体験になったんだと思う……。私の性的なものの……」"
  },
  {
    "name": "直哉",
    "message": "「なるほど……」"
  },
  {
    "name": "稟",
    "message": "「ああ、想像どおりだよ。……すごいね。はぁ、はぁ、はぁぁ……なおくんのこんなになるんだね……」"
  },
  {
    "message": "稟の興奮が高まっていくのが息づかいからも伝わってくる。"
  },
  {
    "name": "稟",
    "message": "「いま、ぴくんって動いた……動いたよ」"
  },
  {
    "name": "稟",
    "message": "「こういうのって、無意識なの？」"
  },
  {
    "name": "直哉",
    "message": "「……さぁな。考えた事もないよ」"
  },
  {
    "name": "稟",
    "message": "「そっか、でも、私がぴくんってなる時も良く分からないから、そういうものなんだね……ん、ん……んんっ」"
  },
  {
    "message": "衣擦れの音がするくらい強く、俺のペニスを手のひらで押し付け、ズボンごと摩擦する。"
  },
  {
    "name": "稟",
    "message": "「この服から浮き出した感じが、ちょっといやらしいかも」"
  },
  {
    "name": "直哉",
    "message": "「そ、そうか？　自分の身体だから良く分からないが……っ」"
  },
  {
    "message": "強い刺激に声が乱れるのを危うくごまかした。"
  },
  {
    "name": "稟",
    "message": "「痛かった？」"
  },
  {
    "name": "直哉",
    "message": "「そんなことはない」"
  },
  {
    "name": "稟",
    "message": "「じゃあ、気持ちよかったとか？」"
  },
  {
    "name": "直哉",
    "message": "「………………」"
  },
  {
    "name": "稟",
    "message": "「って、聞いたりするのはダメだったかな？」"
  },
  {
    "name": "直哉",
    "message": "「いや、だめじゃないけど」"
  },
  {
    "name": "稟",
    "message": "「けど？」"
  },
  {
    "name": "直哉",
    "message": "「答えるのは恥ずかしいもんだな」"
  },
  {
    "name": "稟",
    "message": "「ぞくぞく……」"
  },
  {
    "name": "直哉",
    "message": "「な、なんで笑顔になった？」"
  },
  {
    "name": "稟",
    "message": "「え？　私笑ってましたか？」"
  },
  {
    "name": "直哉",
    "message": "「ああ、すげぇ笑顔だったぞ」"
  },
  {
    "name": "稟",
    "message": "「あははは、そうか、そんな簡単に顔に出ていたのか……」"
  },
  {
    "name": "直哉",
    "message": "「ああ、まんまだったが」"
  },
  {
    "name": "稟",
    "message": "「いや、なんといいますか、なおくんが恥ずかしがっているのを見て、私、ぞくぞくしてしまったのですよ」"
  },
  {
    "name": "直哉",
    "message": "「ぞくぞく？」"
  },
  {
    "name": "稟",
    "message": "「うん、ぞくぞく」"
  },
  {
    "message": "俺の股間に頬ずりするように顔を寄せてくる。"
  },
  {
    "name": "直哉",
    "message": "「うっ、そ、そんな……」"
  },
  {
    "name": "稟",
    "message": "「さっきから私の手の中でトクントクン言ってますけど……」"
  },
  {
    "name": "稟",
    "message": "「……これって、すごく溜まってる証拠ですよねぇ」"
  },
  {
    "message": "ちら、と上目づかいでこっちを見る。"
  },
  {
    "name": "直哉",
    "message": "「な、なにを……いまさら……」"
  },
  {
    "name": "稟",
    "message": "「なおくん溜まってるんですか？」"
  },
  {
    "name": "直哉",
    "message": "「うっ……」"
  },
  {
    "name": "稟",
    "message": "「だとしたら、直接触らないとおさまらないような気がしますよ？」"
  },
  {
    "name": "直哉",
    "message": "「な、なんだ？　羞恥プレイのつもりか？」"
  },
  {
    "name": "稟",
    "message": "「いいえ、そんな事ありませんよ。基本的にお願いです」"
  },
  {
    "name": "直哉",
    "message": "「お願い？」"
  },
  {
    "name": "稟",
    "message": "「そうです。すべて私がやりたい事をなおくんにお願いするだけです」"
  },
  {
    "name": "稟",
    "message": "「私はなおくんのおち○ちんが直に触りたいです\r\nなおくんのおち○ちん、直に触らせてください」"
  },
  {
    "name": "直哉",
    "message": "「っ……」"
  },
  {
    "message": "稟が俺を見つめる。\r\nお願いというわりに、その視線はやたらと挑発的だ……。"
  },
  {
    "name": "直哉",
    "message": "「ああ、いいよ……」"
  },
  {
    "name": "稟",
    "message": "「そうなんだ。なおくんのここ脱がしていいんだね。\r\n私、全部見ちゃうよ？」"
  },
  {
    "name": "直哉",
    "message": "「うっ……い、いちいち恥ずかしい言い方するなぁ」"
  },
  {
    "name": "稟",
    "message": "「そんな事ありませんよ。お願いしてるのですから。\r\n私になおくんのおち○ちん見せてください」"
  },
  {
    "name": "直哉",
    "message": "「……あ、ああ……」"
  },
  {
    "message": "どちらがお願いしているのかさっぱり分からない。\r\n稟はズボンのベルトを緩め、ホックを外す……。"
  },
  {
    "name": "稟",
    "message": "「わぁぁ……」"
  },
  {
    "name": "直哉",
    "message": "「どうした？　驚いたか？」"
  },
  {
    "name": "稟",
    "message": "「う、うん、まぁ、驚いたかなぁ……」"
  },
  {
    "name": "直哉",
    "message": "「なんだ？　なんか、想像してたのと違う。ってヤツか？」"
  },
  {
    "name": "稟",
    "message": "「ううん。そんな事ないよ。想像通りだった！」"
  },
  {
    "name": "直哉",
    "message": "「そ、想像通り……え？」"
  },
  {
    "name": "稟",
    "message": "「うん、おち○ちんって人によって違うって漫画に書いてたから、私は漫画の知識しか無かったから、現実のなおくんのは全然違うんだろうなぁって思ってたんですよ」"
  },
  {
    "name": "稟",
    "message": "「でも、ズボンの上から撫でてた通り、触って想像していたのとまったく同じ」"
  },
  {
    "name": "直哉",
    "message": "「触った上から想像してたのと同じだったのかよ。すごい想像力だな」"
  },
  {
    "name": "稟",
    "message": "「妄想力は半端ありませんからね」"
  },
  {
    "name": "直哉",
    "message": "「だったら？　想像通りな感想は？」"
  },
  {
    "name": "稟",
    "message": "「想像ですか？　うーん。なんと言えばいいのでしょうかねぇ」"
  },
  {
    "message": "稟は俯く。"
  },
  {
    "name": "稟",
    "message": "「な、なおくんの場所から、私の脚って見えるかな？」"
  },
  {
    "name": "直哉",
    "message": "「脚？　まぁ、見えるには見えるが……」"
  },
  {
    "name": "稟",
    "message": "「わ、私の脚、今がくがくしてるよね」"
  },
  {
    "name": "直哉",
    "message": "「あ……」"
  },
  {
    "message": "言われてみれば、稟の脚は震えている。"
  },
  {
    "name": "稟",
    "message": "「さっき、なおくんのここがびくんってするのが無意識かどうか聞いたけど、愚問だったね」"
  },
  {
    "name": "稟",
    "message": "「今、自分の身体で起きているんだもん……」"
  },
  {
    "name": "直哉",
    "message": "「え？」"
  },
  {
    "name": "稟",
    "message": "「感想も何もないよ。頭で考える前に、身体がびくんびくんって反応しているんだもの」"
  },
  {
    "name": "直哉",
    "message": "「そ、そうか……」"
  },
  {
    "name": "稟",
    "message": "「うん」"
  },
  {
    "name": "稟",
    "message": "「だ、だから、もっとよく見せてもらっていいですか？」"
  },
  {
    "name": "直哉",
    "message": "「あ、ああ、お前が望むのならば……」"
  },
  {
    "name": "稟",
    "message": "「はぁぁ…………すごい、すごいなぁ……」"
  },
  {
    "message": "俺の許可をもらった稟が、さらに身を乗り出してきた。"
  },
  {
    "name": "稟",
    "message": "「こんなになって……はぁ……はぁぁ……えっちな形だなぁ……」"
  },
  {
    "message": "稟の声が荒くなっていく。"
  },
  {
    "name": "稟",
    "message": "「あ、あの、そろそろ、触って良いですか……」"
  },
  {
    "name": "直哉",
    "message": "「あ、ああ……」"
  },
  {
    "name": "直哉",
    "message": "「……あ、うわっ？」"
  },
  {
    "name": "稟",
    "message": "「あ……！」"
  },
  {
    "name": "稟",
    "message": "「跳ねた……跳ねるって、こういうことなんだ。\r\n……すごい、私の手の中で、すごく熱いです……」"
  },
  {
    "name": "直哉",
    "message": "「ん……うっ」"
  },
  {
    "message": "顔は赤いくせに、思った以上に冷たい手のひらの感触。\r\nそれが俺の意識にべったりと塗りこまれる。"
  },
  {
    "name": "稟",
    "message": "「はぁはぁ……身体中の血が集まってきてるみたいですね。\r\n本当に充血するのですね。こんな真っ赤になって熱くなって……」"
  },
  {
    "message": "何度も何度も、俺のペニスの感触を確かめるように手のひらを押し付けてくる。"
  },
  {
    "name": "稟",
    "message": "「ん……はぁぁ、熱い」"
  },
  {
    "message": "下から上にゆっくりとなぞり、雁首のくびれをそっと撫でて。"
  },
  {
    "name": "稟",
    "message": "「わ、すごくえっちぃ感触です。もう少し強くふれて良いですか？」"
  },
  {
    "message": "俺は小さく頷く。"
  },
  {
    "name": "直哉",
    "message": "「んんッ！」"
  },
  {
    "message": "根元のあたりをギュッと握られて、声が漏れた。"
  },
  {
    "name": "稟",
    "message": "「あ、あ……すごい」"
  },
  {
    "name": "直哉",
    "message": "「い、いきなり刺激するから……」"
  },
  {
    "name": "稟",
    "message": "「痛かったですか？」"
  },
  {
    "name": "直哉",
    "message": "「いや、痛くはない……くっ」"
  },
  {
    "name": "稟",
    "message": "「えへへ、なおくんもあえぎ声とか出すんだ……\r\nはぁぁ……すごくえっちぃ声だった」"
  },
  {
    "name": "直哉",
    "message": "「そ、そんな風に言うなぁ……」"
  },
  {
    "name": "稟",
    "message": "「なおくん、もっと声出していいよ。\r\n私、なおくんのそういう声聞きたい」"
  },
  {
    "name": "直哉",
    "message": "「お、俺は、男のあえぎ声とか願い下げだよ……」"
  },
  {
    "name": "稟",
    "message": "「なおくんは嫌なの？　でもここはすごくいやらしい音になってるよ？」"
  },
  {
    "message": "稟が手をゆっくりと、だが確実にスライドさせていく。"
  },
  {
    "name": "稟",
    "message": "「ほら、音聞こえる？　くちゅ、くちゅって、すごくいやらしい音です。\r\nふぅぅぅ…………っ、なんかなおくんからいやらしい匂いがしてきたよ」"
  },
  {
    "name": "直哉",
    "message": "「んっ、くぅっ……うっ！」"
  },
  {
    "name": "稟",
    "message": "「また声出たよ。やっぱりなおくんの声ぞくぞくする。\r\nもっと気持ちいい声出してくれないかな？」"
  },
  {
    "name": "直哉",
    "message": "「だ、だから、そういうのは、俺は……くっ」"
  },
  {
    "name": "稟",
    "message": "「ぴくぴくするって、もっと小刻みな感じかと思ったけど、違うね。あとぴくぴくするたびにえっちな汁が出てくる。いやらしいね。男の子のここってこんなにいやらしいんだね」"
  },
  {
    "message": "先濡れ液で湿り始めた俺の亀頭を稟は指の間に挟んでつまむ。"
  },
  {
    "name": "直哉",
    "message": "「うっ」"
  },
  {
    "name": "稟",
    "message": "「全身がびくんってしました。お○んちんの先っぽがこんなに充血して……。\r\nああ、どうしよう。たとえばなおくんのここ、息で吹きかけてみたらどんな感じだろう」"
  },
  {
    "name": "直哉",
    "message": "「あ、おい……んッ！」"
  },
  {
    "name": "稟",
    "message": "「ふぅぅぅ…………っ…………」"
  },
  {
    "name": "直哉",
    "message": "「あっ、くっ……」"
  },
  {
    "name": "稟",
    "message": "「気持ちいい？　息だけでも気持ちいいのかな？」"
  },
  {
    "name": "直哉",
    "message": "「だ、だって……うあッ」"
  },
  {
    "name": "稟",
    "message": "「息をふーってしてるだけですよ？　それだけ敏感になっているって事ですよね」"
  },
  {
    "name": "直哉",
    "message": "「指の間で思いっきり握ってるから……」"
  },
  {
    "name": "稟",
    "message": "「うん、さきっぽのえっちぃ部分を指で押し出したんだよ。そしたら敏感になるかなぁ、って思ってね」"
  },
  {
    "name": "稟",
    "message": "「なおくん、このまま手動かしていいかな？」"
  },
  {
    "name": "直哉",
    "message": "「あ、いや、ま、待っ、くぅぅぅっ」"
  },
  {
    "name": "稟",
    "message": "「あ、ごめん。動かしちゃった。でも、なおくんのこここんなに濡れて、こんなにいやらしいんだもん。私の指だって動いちゃうよ……」"
  },
  {
    "name": "直哉",
    "message": "「あっ、あうっ……あ」"
  },
  {
    "name": "稟",
    "message": "「すごい、くちょくちょ音が鳴っているよ。いやらしいねぇ。お○んちんこんなになるんだねぇ。女の子と変わらないよ」"
  },
  {
    "message": "心地いい強さで指に挟まれて、前後にゆっくりスライドさせられる。"
  },
  {
    "name": "直哉",
    "message": "「はぁはぁ……くっ」"
  },
  {
    "name": "稟",
    "message": "「あぁ、手の動きに合わせて、なおくんの息がいやらしくなってるよ。はぁはぁ、なおくんの息っていやらしいねぇ」"
  },
  {
    "name": "直哉",
    "message": "「そ、そんな事は……」"
  },
  {
    "message": "そんなに強い摩擦ではないのに、まるで理性を搾り出されるみたいだ。"
  },
  {
    "name": "稟",
    "message": "「手首のスナップを利かせるといいのかな……こんな感じかな？」"
  },
  {
    "name": "稟",
    "message": "「こう……しこしこって…………わ、またびくんってしてえっちな汁が出てきたよ」"
  },
  {
    "message": "俺の反応を見ながら、探るように指先を動かす。"
  },
  {
    "name": "稟",
    "message": "「すごいですね……お○んちん、いつもこんなになるんですか？」"
  },
  {
    "name": "直哉",
    "message": "「じ、自分でする時は、さすがにここまでならな……くっ」"
  },
  {
    "name": "稟",
    "message": "「そうですよねぇ。こんないやらしい汁が出てたら、オナニーした後の掃除とか大変すぎますもの」"
  },
  {
    "name": "稟",
    "message": "「でも、今日は特別なんだね。\r\nだから、いくら汚してもいいんだよ。私の手をいくらでもなおくんので汚して……」"
  },
  {
    "name": "直哉",
    "message": "「あうっ」"
  },
  {
    "name": "稟",
    "message": "「はぁぁ……、すごいすごい。おち○ちんぐちょぐちょいって、すごくいやらしいよぉ。なおくんすごくいやらしい……」"
  },
  {
    "message": "楽しそうにしながらも、俺を気遣うような稟の表情。"
  },
  {
    "message": "強制愛撫と奉仕の中間にあるような指先の快感が、俺の意識をゆっくり塗りつぶしていく。"
  },
  {
    "name": "稟",
    "message": "「すごい、手がぬるぬるだよ。なおくんのお○んちんってほんとうにいやらしいんだねぇ。くっ……うぅ……」"
  },
  {
    "message": "稟の息がどんどん荒くなっていく。"
  },
  {
    "message": "このままやられっぱなしというのもしゃくに障った。"
  },
  {
    "message": "俺のペニスの変化を記憶に焼き付けようとするかのように、凝視している稟に問いかける。"
  },
  {
    "name": "直哉",
    "message": "「こ、これ思い出して、くっ、稟は自分でもする気なのか？」"
  },
  {
    "name": "稟",
    "message": "「え……」"
  },
  {
    "name": "稟",
    "message": "「…………………………」"
  },
  {
    "name": "稟",
    "message": "「…………そんなの、しないわけがないじゃないですか」"
  },
  {
    "name": "直哉",
    "message": "「そうなんだ」"
  },
  {
    "name": "稟",
    "message": "「当たり前だよ。なおくんのこんな姿見られて、自分でしないわけないよ……はぁ、はぁぁ……すごい……なおくんの」"
  },
  {
    "message": "我慢汁を垂らしたペニスと俺の顔を、交互に見比べる。"
  },
  {
    "name": "稟",
    "message": "「………………はぁ、はぁぁ……すごく熱いよぉ……」"
  },
  {
    "name": "稟",
    "message": "「なおくんの身体……こんなに成長してたんだ……はぁ、はぁぁ……」"
  },
  {
    "name": "稟",
    "message": "「…………ん、ん……はぁ、はぁ、はぁぁ……」"
  },
  {
    "message": "ペニスをしごきながら、次第に稟の息づかいが荒くなってくる。"
  },
  {
    "name": "稟",
    "message": "「ん……んッ、ん…………ん、ん、ん…………」"
  },
  {
    "name": "稟",
    "message": "「んっ……んんン…………ふぅー……ふぅーー……んんン……んんッ」"
  },
  {
    "name": "稟",
    "message": "「んぁ……ふぅ……ふぅっ、ふぅ、ふゥ……ふゥ、ふぅ、ふぅ……んん゛ッ……ん……」"
  },
  {
    "name": "稟",
    "message": "「んあァァ……」"
  },
  {
    "name": "直哉",
    "message": "「くっ、り、稟……お、お前……自分で……」"
  },
  {
    "name": "稟",
    "message": "「あはは、バレましたか？　くうぅ……ふぅ……んん゛ッ」"
  },
  {
    "name": "稟",
    "message": "「だ、だって……こんなの我慢出来るわけないじゃないですか……んぁ……ふぅ……ふぅっ、んあァァ……こんないやらしいなおくん見て、我慢なんて出来ないよ」"
  },
  {
    "name": "直哉",
    "message": "「が、我慢出来ないぐらい興奮してたのか？　くっ」"
  },
  {
    "name": "稟",
    "message": "「くぅぅ……ご、ごめんなさいぃ……」"
  },
  {
    "name": "稟",
    "message": "「……………もったいないから、させてください」"
  },
  {
    "name": "直哉",
    "message": "「何をさせてほしいんだ？」"
  },
  {
    "name": "稟",
    "message": "「んっ……え？」"
  },
  {
    "name": "直哉",
    "message": "「俺ばかり羞恥責めじゃ不公平だろ。くっ……、何をしたいか、はっきり言えよ……」"
  },
  {
    "name": "稟",
    "message": "「え？　そんなぁ。ふゥ……ふゥ、ふぅ、ふぅ……んん゛ッ」"
  },
  {
    "name": "直哉",
    "message": "「何をさせてほしいんだ？」"
  },
  {
    "name": "稟",
    "message": "「お、オナ……。\r\nい、言わないとダメかなぁ？　ん、んんっ……」"
  },
  {
    "name": "直哉",
    "message": "「実際、今も手動かしてるだろ……」"
  },
  {
    "name": "稟",
    "message": "「う、うん……手止まらないんだよ……くぅ…はうぅん……ふゥ……ふゥ、ふぅ、ふぅ……んん゛ッ」"
  },
  {
    "name": "直哉",
    "message": "「だったら言えよ」"
  },
  {
    "name": "稟",
    "message": "「なおくんいじわるです……。もう知ってるのだからいいじゃないですかぁ……はぁ、はゥ……ふぅ、はぅ……んん゛ッ」"
  },
  {
    "message": "その間も稟の手はパンツの中でせわしなく動き続けている。"
  },
  {
    "name": "直哉",
    "message": "「知っているというか、丸見えだけどな……くっ」"
  },
  {
    "message": "稟のしごく手が速くなる。"
  },
  {
    "name": "稟",
    "message": "「はぁ、はぁぁ……熱くて硬くて……ヌルヌルしててえっちぃだったから……」"
  },
  {
    "name": "直哉",
    "message": "「それで、スイッチ入ったのか？」"
  },
  {
    "name": "稟",
    "message": "「あぁ、あぁぁ……ううん、最初からです……ん、んっ、んん……ごめんなさい……はぁ、はぁ、はぁぁ……」"
  },
  {
    "name": "稟",
    "message": "「あ、匂い……くんくん、こんな感じなんだ……はぁ、はぁぁ……っ、ンっ、ンンっ……」"
  },
  {
    "message": "鼻を鳴らしながら、もう顔が接触しそうなくらい近くに寄ってきている。"
  },
  {
    "name": "稟",
    "message": "「さっきから気になってたんだ。でもこんなあからさまに匂いかいでたら、おかしいと思われるとおもって……くぅ…はうぅん……はゥ……ふゥ、ふぅ、はぅ……ん゛ッ」"
  },
  {
    "name": "稟",
    "message": "「でも我慢出来ないよぉ。なおくんのここの匂い良くかいでもいいですか？」"
  },
  {
    "name": "直哉",
    "message": "「あ、ああ……」"
  },
  {
    "name": "稟",
    "message": "「くんくん……すぅぅぅ、はぁぁぁ、すごい、いやらしい匂い。すごくいやらしいよぉ。くぅ…ふぅん……はゥ……はゥ」"
  },
  {
    "message": "すみずみまで稟が俺の下半身の匂いを嗅いでいる。"
  },
  {
    "name": "稟",
    "message": "「はぁ、はぁ、とろっとしてきた……さっきより蕩けちゃってますよ……はぁ、はぁぁ、いやらしいよぉ。いやらしすぎだよぉ……」"
  },
  {
    "name": "稟",
    "message": "「くんくん……くんくん……ん、ンン……ッッ……はぁぁ……ァ……」"
  },
  {
    "message": "鼻の音にまじって、くちゅくちゅとショーツの中の濡れる音。"
  },
  {
    "name": "直哉",
    "message": "「り、稟も、気持ちいいのか？」"
  },
  {
    "name": "稟",
    "message": "「うん……すごいよ。すごくとろけちゃいそうなんだよ……」"
  },
  {
    "name": "直哉",
    "message": "「オナニーで？」"
  },
  {
    "name": "稟",
    "message": "「うん、なおくんのおちん○んしごきながら、オナニーするの気持ちいいよぉ……はうん、ふゥ……ふぅ、ふぅ……んん゛ッぁ」"
  },
  {
    "name": "直哉",
    "message": "「や、やっとオナニーって言ったな……くっ」"
  },
  {
    "name": "稟",
    "message": "「うん、だって、なおくんのおち○ちんの匂いかいでたら……頭が痺れてきて……いやらしすぎなんだもんなおくんのここって」"
  },
  {
    "name": "直哉",
    "message": "「思わず口に出してしまったと」"
  },
  {
    "name": "稟",
    "message": "「はぁ、はぁぁ……そんなの、恥ずかしいのに………」"
  },
  {
    "name": "稟",
    "message": "「だから…………余計に感じちゃうのかもしれません…くぅっ」"
  },
  {
    "name": "直哉",
    "message": "「いつもより？」"
  },
  {
    "name": "稟",
    "message": "「いつもなんて比べものにならないよぉ、すごく、すごくトロトロですよ……私の…………」"
  },
  {
    "name": "稟",
    "message": "「………………」"
  },
  {
    "message": "あえぎ声だけで答えない稟。"
  },
  {
    "message": "口をぱくぱくさせて何か言う。"
  },
  {
    "name": "稟",
    "message": "「…………おま……こ……」"
  },
  {
    "name": "稟",
    "message": "「あうっっ、恥ずかしいぃぃ……くはぁ」"
  },
  {
    "name": "稟",
    "message": "「でも、気持ちいいですぅ……はぁはぁ、くぅん……はゥ……ふゥ、んん゛ッ」"
  },
  {
    "message": "うっとりした顔の稟が、ショーツの中の手を差し伸ばしてきた。"
  },
  {
    "message": "とろっとした透明な粘液が、指の間で糸を引いている。"
  },
  {
    "name": "直哉",
    "message": "「……ッッ！」"
  },
  {
    "name": "稟",
    "message": "「こんななってしまっています…………私、ヘンタイさんですよね」"
  },
  {
    "message": "ふたたび下着の中に差し入れた指先が、俺の耳にまで水音を届かせる。"
  },
  {
    "name": "稟",
    "message": "「でもそんなやめられません。なおくんのを感じてたら、止める事なんて出来ない……はぁ、はぁ、はっ、はっ、はっ、はぁぁ……」"
  },
  {
    "name": "稟",
    "message": "「ああ……くぅん……ふゥ……んっ、な、なおくんのこれって、もうエッチできる状態なんですよね？」"
  },
  {
    "message": "だまってうなずくと、稟のまなざしがますますウットリと細められる。"
  },
  {
    "name": "稟",
    "message": "「本当なら、これが……入っちゃうんだ……」"
  },
  {
    "name": "稟",
    "message": "「すごく太い……それに長くて、硬くて……あぁぁ、熱いの……ここに入ったら、どうなっちゃうのかな……」"
  },
  {
    "name": "稟",
    "message": "「あは、こんな風に擦るといいですか？　それとも……ん、ンッ……」"
  },
  {
    "message": "また、ショーツの中でクチョクチョさせていた手を、稟が俺に見せつける。"
  },
  {
    "name": "稟",
    "message": "「これ……私のです。私のいやらしいお汁です……」"
  },
  {
    "name": "稟",
    "message": "「なおくんと同じ……ううん。それ以上に濡れちゃってます……」"
  },
  {
    "name": "稟",
    "message": "「だから……ほら、私のヌルヌルをなおくんのに……混ぜちゃうの……」"
  },
  {
    "message": "それから、そのヌルヌルの手で俺のペニスをしっかりと握り……。"
  },
  {
    "name": "稟",
    "message": "「あぁぁ……なおくんと混ざっちゃった……えっちぃです……」"
  },
  {
    "message": "何度も何度も、激しく手首をスナップさせる。"
  },
  {
    "name": "直哉",
    "message": "「あ、もうちょっと……」"
  },
  {
    "name": "稟",
    "message": "「速いほうがいいですか？」"
  },
  {
    "name": "直哉",
    "message": "「ぎゃ、逆っ……さ、さっきから耐えてるんだから、くぅ」"
  },
  {
    "name": "稟",
    "message": "「そんなぁ、そんなことしなくていいですよ……ほら、ぴゅーってなるんですよね。出してくださいよ。私、なおくんが射精するところみたいです」"
  },
  {
    "message": "さらに俺を追い込むように右手の動きを速くしてくる。"
  },
  {
    "name": "稟",
    "message": "「ぴゅーーって出して、気持ちよくなってください……ん、ん、んっ……あぁ、あぁぁ……」"
  },
  {
    "message": "まるでよだれでも垂らしそうなくらい、俺のペニスに全神経を集中させているみたいだ。"
  },
  {
    "name": "稟",
    "message": "「はぁ、はぁ、はぁぁ……あ、あ、すごい……私も、私もすごくなっちゃってる……あぁ、はぁ、はぁ、はぁぁ……もう良く分からないよぉ」"
  },
  {
    "name": "直哉",
    "message": "「どのぐらい？」"
  },
  {
    "name": "稟",
    "message": "「それは……んぁぁ、はぁ、はぁ、も、もうヌルヌルすぎて、どこがどこだか分からない……ぐらい敏感で、あぁ、下着なんて、全然役に立たないぐらい……あぁ、んぁ、んぁ、んんぁ……」"
  },
  {
    "message": "喘ぎが大きくなった。\r\n明らかに発情した稟の顔が俺のペニスの向こう側にある。"
  },
  {
    "name": "稟",
    "message": "「あぁぁ、あぁーーぁぁ……えっち……えっち…………えっちなことしてる……なおくんとえっちぃこと……」"
  },
  {
    "name": "直哉",
    "message": "「あ……待て……ん、ンッ！」"
  },
  {
    "message": "イきそうになった。\r\n必死に腹筋でこらえるのを見た稟が、さらに手首のスナップを速くする。"
  },
  {
    "name": "稟",
    "message": "「はぁ、はぁ、はぁ、イきそう……イけますか？　これでイける？」"
  },
  {
    "name": "直哉",
    "message": "「………………あ、ああ」"
  },
  {
    "name": "稟",
    "message": "「あぁぁ、イっちゃうんですね……なおくん、私の手で射精するんだ……はぅん…くふぅ……ふゥ……はぅ……ん゛ッん……」"
  },
  {
    "message": "ヌチュヌチュと、部屋の中にお互いの愛液のからみあう音と、荒い呼吸が響く。"
  },
  {
    "message": "先に音を上げたのは、稟のほうだった。"
  },
  {
    "name": "稟",
    "message": "「はぁッ、はぁッ……あぁぁ、もうダメだ、ダメだよ。全然、もう耐えられない。気持ち良すぎるよぉ……くぅ……ふゥん……はふゥ、はふぅ……ん」"
  },
  {
    "name": "稟",
    "message": "「だめ、ダメ、駄目だよ。全然だめだ。ごめん……私もイっちゃう……ごめんなさい、先にイっちゃうぅっ」"
  },
  {
    "name": "稟",
    "message": "「はぁはぁ、くふぅ、あうっ、ど、どうしたらいいですか、先にイくの悪くて……あぁ、あぁ、あぁぁ……我慢してます、してるけどっ……！」"
  },
  {
    "name": "直哉",
    "message": "「そんなのいいから、稟も気持ちよくなれよ」"
  },
  {
    "name": "稟",
    "message": "「そんな、でも早い……あぁぁ……だめだめ、もうだめです。あっあっああが、我慢、がま……んきっ……あ、ああ、だめだめいく……イくぅ…………っくぅぅ……！」"
  },
  {
    "name": "直哉",
    "message": "「本当に、イくときはすぐだな……」"
  },
  {
    "name": "稟",
    "message": "「…………あぁぁ、ごめんなさい。ごめんなさい。でも、だめ、だめです、イクイク……イきます……ごめんなさい、ごめんなさいぃっ」"
  },
  {
    "name": "直哉",
    "message": "「俺もだ……稟ッ！」"
  },
  {
    "message": "俺の顔を見上げたまま、稟の表情が切なそうに引きつり……。"
  },
  {
    "name": "稟",
    "message": "「あぁぁ、なおくん……ィッッ…………ぐッ！！」"
  },
  {
    "name": "稟",
    "message": "「んっっ…………んん゛ーーーーーーーーッッ！！」"
  },
  {
    "message": "ギューッとペニスが圧迫される。\r\n俺にしがみついたまま、稟が何度も身体を震わせた。"
  },
  {
    "message": "そして、その手の締め付けが緩むのと同じタイミングで。"
  },
  {
    "name": "直哉",
    "message": "「ん………………ッッ、く！！」"
  },
  {
    "message": "全身が震えるような衝撃とともに、大量の精液が射ち出される。"
  },
  {
    "name": "稟",
    "message": "「はぁーーっ、はぁぁーーーっ……はぁぁ……うあ？　あ、あ、あぁぁ……すごい…………！」"
  },
  {
    "message": "稟の手のひらに包まれたまま、何度も何度も、濁った熱い欲望がほとばしっていく。"
  },
  {
    "name": "稟",
    "message": "「あぁ、あぁぁ……出てる、たくさん出てる……まだシコシコする？　してもいいですか？」"
  },
  {
    "message": "射精中のペニスをしごかれて、息が詰まる。\r\nそんな俺の反応を見た稟が、握る力を抜いて、やさしくさすってくる。"
  },
  {
    "name": "稟",
    "message": "「はぁ、はぁぁ……射精してる……なおくんが射精……あぁぁ、すごい……見ちゃった……本当にしちゃってる……」"
  },
  {
    "name": "稟",
    "message": "「あ、あぁ……変な感じ、また…………はぁ、はぁぁ……ん、くッ…………んッッ！！　あ、また、だ。まただめ、だめ、そんなぁ、くぅぅぅ、またなんて、ひぐぅ…はうぅん……ふゥ……ふゥ、ふぅ、ふぅ……んん゛ッ」"
  },
  {
    "name": "稟",
    "message": "「あ、ああ、我慢できないぃぃ、はぅぅぅぅんっんっっ…………んん゛ーーーーーーーーッッ！！」"
  },
  {
    "message": "俺の射精を手伝いながら、稟はもう一度腰をびくびくッと跳ねさせて、小さな絶頂を迎えた。"
  },
  {
    "name": "稟",
    "message": "「はぁーーーぁぁ……はぁ、はぁ、はぁぁ……」"
  },
  {
    "name": "直哉",
    "message": "「もしかして二回イった？」"
  },
  {
    "name": "稟",
    "message": "「う、うん、なおくんがぴゅーって出してるの見てたら、いやらしすぎちゃって……我慢できなかったよ」"
  },
  {
    "name": "直哉",
    "message": "「け、結構イク時って派手なんだな……」"
  },
  {
    "name": "稟",
    "message": "「な、なんですかそれ」"
  },
  {
    "name": "直哉",
    "message": "「いや、いつぞや、漫画みたいに大声でオナニーしたりしないって言ってたからさ」"
  },
  {
    "name": "稟",
    "message": "「う゛ーいじわる……です」"
  },
  {
    "name": "稟",
    "message": "「だ、だって、一人でしてるわけじゃないんですから……、\r\nそりゃ、なおくんの見てたら興奮もしますし……」"
  },
  {
    "name": "直哉",
    "message": "「そんなに興奮した？」"
  },
  {
    "name": "稟",
    "message": "「そ、そんな事いいじゃないですかっ、そんな事聞くのは無粋です。\r\nあ、そんな事よりも、まだ出てますよ」"
  },
  {
    "message": "射精は終わったが、中に残っていた精液がトロリと滲み出してくる。"
  },
  {
    "name": "稟",
    "message": "「次は、なおくんがもっと喜ぶところに出したほうがよいですよね？」"
  },
  {
    "name": "直哉",
    "message": "「喜ぶとこ？」"
  },
  {
    "name": "稟",
    "message": "「はい。えと……顔とか、お口とか、おっぱいとか」"
  },
  {
    "name": "稟",
    "message": "「あとは…………ふふふ」"
  },
  {
    "name": "直哉",
    "message": "「な、なんだよ」"
  },
  {
    "name": "稟",
    "message": "「ナイショです……あ、またひくんってなった」"
  },
  {
    "message": "上気させた顔のまま、稟が俺のをシコシコとしごきだす。"
  },
  {
    "name": "直哉",
    "message": "「え、まだするのか？」"
  },
  {
    "name": "稟",
    "message": "「だって、硬いですよ？」"
  },
  {
    "message": "確かにまったく萎える気配がない。\r\nだが、これ以上やると歯止めがきかなくなりそうで怖くもあるのだが。"
  },
  {
    "name": "稟",
    "message": "「もうちょっと勃ってるのを、見てみたくて……ちゃんと観察しておきたいですし」"
  },
  {
    "name": "稟",
    "message": "「ダメですか？」"
  },
  {
    "name": "直哉",
    "message": "「ダメじゃないが……はうッ！」"
  },
  {
    "name": "稟",
    "message": "「あ、敏感になってるんだ……じゃあ、優しくですね。\r\n……ふふふ、シコシコするの気持ちいーい？」"
  },
  {
    "name": "直哉",
    "message": "「急に手のひらで転がすな」"
  },
  {
    "name": "稟",
    "message": "「だって、そういうことをしているのですから、それは仕方ないじゃないですか」"
  },
  {
    "name": "稟",
    "message": "「それに、受身で感じてるなおくんって、かわいいし。\r\nあそこ触られると、なおくんも普通じゃいられなくなるんだって、わかりましたから」"
  },
  {
    "message": "なにか言い返したいが、確かに稟の言うとおりだ。\r\n俺の肉体は、ふたたびシコシコされて、また射精したがっている。"
  },
  {
    "message": "だめだ。肉体の快楽に理性が抗えない。\r\n稟の手の動きに身を任せ、目を閉じようとしたところで……。"
  },
  {
    "name": "稟",
    "message": "「あ！」"
  },
  {
    "name": "直哉",
    "message": "「え？」"
  },
  {
    "name": "稟",
    "message": "「大変ですよ！　もう学校に行かないと……」"
  },
  {
    "name": "直哉",
    "message": "「っと、遅刻しそうだな？」"
  },
  {
    "name": "稟",
    "message": "「あ、はい、今日はおしまいです！」"
  },
  {
    "name": "直哉",
    "message": "「…………え？　あ、ああ」"
  },
  {
    "name": "稟",
    "message": "「くすくす……」"
  },
  {
    "name": "直哉",
    "message": "「なんだよ」"
  },
  {
    "name": "稟",
    "message": "「なおくん、最後までしたかったんですか？」"
  },
  {
    "name": "直哉",
    "message": "「……っ！？」"
  },
  {
    "message": "理性は早く家を出ろと言っているのに、感情が声に乗ってしまったようだ。"
  },
  {
    "name": "稟",
    "message": "「がっかりした顔のなおくん、なんか得した気分です」"
  },
  {
    "name": "直哉",
    "message": "「そんな顔じゃないぞ、これは遅刻を心配してるだけで」"
  },
  {
    "name": "稟",
    "message": "「あ、そうだったんですか」"
  },
  {
    "name": "直哉",
    "message": "「…………それだけとは言い切れない部分も、あるにはあるが」"
  },
  {
    "name": "稟",
    "message": "「くすくす……」"
  },
  {
    "message": "射精させられたせいかもしれないが、なんだか稟に遊ばれている気がする。"
  },
  {
    "name": "稟",
    "message": "「あ、なおくん、ちょっと待ってください……ソレ、まだしまわないで」"
  },
  {
    "name": "直哉",
    "message": "「な、なに？」"
  },
  {
    "name": "稟",
    "message": "「えと……」"
  },
  {
    "message": "そそくさ……と近寄ってきた稟が、俺の前で立てひざをつく。\r\nもしや、このまま続きを……？"
  },
  {
    "name": "稟",
    "message": "「学校に行ってる間は、我慢してくださいね……ん」"
  },
  {
    "name": "稟",
    "message": "「ん…………ちゅっ」"
  },
  {
    "name": "直哉",
    "message": "「──！？」"
  },
  {
    "name": "稟",
    "message": "「お○んちんにキスしてしまいました……」"
  },
  {
    "name": "直哉",
    "message": "「き、キス……」"
  },
  {
    "name": "稟",
    "message": "「さ、さ、さあ、そんなことはいいですから、急いで行きましょうっ」"
  },
  {
    "name": "直哉",
    "message": "「あ、ああ……」"
  },
  {
    "message": "自分に起こった事が理解できずに、言われるがまま慌てて俺はズボンをはいて登校の準備をする。"
  },
  {
    "name": "直哉",
    "message": "「ん……」"
  },
  {
    "message": "股間が疼いた。"
  },
  {
    "message": "あの稟のくちびるが俺のあそこの部分に……。"
  },
  {
    "message": "この状態で、本当に我慢なんて出来るのだろうか？"
  }
]