[
  {
    "name": "優美",
    "message": "「今日も良い天気だ」"
  },
  {
    "name": "里奈",
    "message": "「風景画だからねぇ。天気が良いと助かる」"
  },
  {
    "name": "優美",
    "message": "「でも、里奈はあまり日光にあたると良くないから、ちゃんと日陰にいなきゃだめだよ」"
  },
  {
    "name": "里奈",
    "message": "「そんな心配しなくても、十分自分の身体は分かってるから大丈夫だって」"
  },
  {
    "name": "優美",
    "message": "「そっか……」"
  },
  {
    "name": "優美",
    "message": "「でも、何で里奈はこの屋上からの風景を題材に選んだの？」"
  },
  {
    "name": "里奈",
    "message": "「描いてるのを見てるのだから、だいたい予想つくんじゃないの？」"
  },
  {
    "name": "優美",
    "message": "「ラフだと良く分からない」"
  },
  {
    "name": "里奈",
    "message": "「ここからだと、糸杉の森と桜の森が重なるんだよ」"
  },
  {
    "name": "優美",
    "message": "「あ、そういえば……」"
  },
  {
    "name": "里奈",
    "message": "「今は夏だから分からないじゃない。でもさ、春の桜が満開の季節だと、桜の森の奥に、黒い糸杉の姿が見える」"
  },
  {
    "name": "里奈",
    "message": "「春にね。この屋上に立って、すぐに写真撮ったんだよ」"
  },
  {
    "name": "優美",
    "message": "「写真を？」"
  },
  {
    "name": "里奈",
    "message": "「そう、私はこの弓張の三年間で、ここから桜と糸杉を描き続けるんだってね」"
  },
  {
    "name": "優美",
    "message": "「そっか……」"
  },
  {
    "name": "里奈",
    "message": "「だから、ムーア展どうこうって、あまり興味が無いんだよね。特に今年は……」"
  },
  {
    "name": "里奈",
    "message": "「写真でしか、桜が咲いている風景は持ってないし……」"
  },
  {
    "name": "優美",
    "message": "「今年は納得出来るものが出来る自信が無い？」"
  },
  {
    "name": "里奈",
    "message": "「自信って言うか、自分が納得出来る作品が出来ればそれでいいんだよ。\r\nとりあえず来年は、ちゃんと春にここで桜と糸杉を直に見ながら写生したいな」"
  },
  {
    "name": "優美",
    "message": "「里奈はまだ糸杉が好きなの？」"
  },
  {
    "name": "里奈",
    "message": "「うん、糸杉は好きだよ。でも今は桜だって好きだ」"
  },
  {
    "name": "優美",
    "message": "「そっか……」"
  },
  {
    "name": "里奈",
    "message": "「さぁ、とりあえず描き始めますか」"
  },
  {
    "name": "優美",
    "message": "「とりあえず道具の用意を……」"
  },
  {
    "message": "私達は絵を描く用意をしはじめる。"
  },
  {
    "name": "優美",
    "message": "「そういえば、今日は夢を見たの？」"
  },
  {
    "name": "里奈",
    "message": "「うん、たぶん見たと思う」"
  },
  {
    "name": "優美",
    "message": "「あまり覚えてない？」"
  },
  {
    "name": "里奈",
    "message": "「どうなんだろ……覚えてると言えば覚えてるのだけど……」"
  },
  {
    "message": "私は言葉を濁す。"
  },
  {
    "message": "はっきり言えば、覚えている。"
  },
  {
    "message": "まるで、自分が経験した事かの様に覚えている。"
  },
  {
    "message": "あの夢は一体なんなのだろう……。"
  },
  {
    "name": "義貞",
    "message": "「来ていただけましたか」"
  },
  {
    "name": "伯奇",
    "message": "「“[txruby text=\"こよい\"]今宵[txruby]、枯れた桜の丘で会いたい”と[txruby text=\"ふみ\"]文[txruby]に書かれていましたので、言われた通りに参上いたしました」"
  },
  {
    "name": "義貞",
    "message": "「ははは、言われた通りか、貴方らしい」"
  },
  {
    "name": "伯奇",
    "message": "「貴方らしい？」"
  },
  {
    "name": "義貞",
    "message": "「いや、こちらの話です。それにしてもここの桜はどれも老木だから、もう花を咲かせない。皆気味悪がって、夜にはこの丘を訪れない」"
  },
  {
    "name": "伯奇",
    "message": "「この丘の名はなんと？」"
  },
  {
    "name": "義貞",
    "message": "「名は無い。ただの枯れ木の丘」"
  },
  {
    "name": "義貞",
    "message": "「[txruby text=\"ひとめ\"]人目[txruby]を[txruby text=\"しの\"]忍[txruby]んで会うには、絶好の場所ではあります」"
  },
  {
    "name": "義貞",
    "message": "「いや。そんなことより先に礼を申し上げるべきでしたな」"
  },
  {
    "name": "伯奇",
    "message": "「礼？」"
  },
  {
    "name": "義貞",
    "message": "「はい。父の凶夢を取り除いて頂き、まことにかたじけのうございます」"
  },
  {
    "name": "伯奇",
    "message": "「それは伯奇の役目」"
  },
  {
    "name": "義貞",
    "message": "「そう言わずに。礼くらい言わせてください」"
  },
  {
    "name": "伯奇",
    "message": "「……」"
  },
  {
    "name": "義貞",
    "message": "「それにしても、貴方が来てくれるとは思いませんでした」"
  },
  {
    "name": "伯奇",
    "message": "「何故でしょうか？」"
  },
  {
    "name": "義貞",
    "message": "「初めて逢ったあのとき、私にあまり良い印象を持たれているとは思わなかったので」"
  },
  {
    "name": "伯奇",
    "message": "「伯奇に感情はないのです」"
  },
  {
    "name": "義貞",
    "message": "「そうでしたな。なるほど、だからあの時に良い印象も悪い印象も持たなかったと」"
  },
  {
    "name": "伯奇",
    "message": "「はい」"
  },
  {
    "name": "義貞",
    "message": "「その事ですが、私にはいささか信じられない。\r\n貴方にまったく感情が欠落しているなど……」"
  },
  {
    "name": "義貞",
    "message": "「そういえば、夢張りの巫女は。喋る事、見る事、聞く事を禁じられていると聞く、だが、貴方は私と喋ったし、見たし、声も聞いた」"
  },
  {
    "name": "伯奇",
    "message": "「……」"
  },
  {
    "name": "義貞",
    "message": "「それなら伯奇殿は全ての禁を破ってしまった事になる。\r\n何故、心を持たぬ貴方がその様な事をした？」"
  },
  {
    "name": "伯奇",
    "message": "「分かりませぬ……」"
  },
  {
    "name": "義貞",
    "message": "「分からないと？」"
  },
  {
    "name": "伯奇",
    "message": "「はい……」"
  },
  {
    "message": "分からない。"
  },
  {
    "message": "私には本当に分からない。"
  },
  {
    "message": "何故、私はあの時に目をあけたのであろうか？"
  },
  {
    "message": "何故、私はあの時に、彼の声に耳を傾けたのだろうか？"
  },
  {
    "message": "何故、言葉を交わしたのだろうか？"
  },
  {
    "message": "そして、何故、今、私はここに立っているのだろうか？"
  },
  {
    "name": "伯奇",
    "message": "「分からない……」"
  },
  {
    "message": "花一つ咲かない桜の丘、その老木の下にひとりたたずむ彼の姿を[txruby text=\"おも\"]想[txruby]ったとき。"
  },
  {
    "message": "私の足は、この丘を目指して歩き始めていた。"
  },
  {
    "message": "何故、私はその様な事をしたのだろうか？"
  },
  {
    "name": "義貞",
    "message": "「私のせいで伯奇殿は禁を破ってしまった」"
  },
  {
    "name": "義貞",
    "message": "「ですが、私はその事を謝りません」"
  },
  {
    "name": "義貞",
    "message": "「私は伯奇殿とこうしていられることが嬉しい。\r\nだから、謝る事が出来ない」"
  },
  {
    "name": "伯奇",
    "message": "「私といる事が……嬉しい……」"
  },
  {
    "message": "“嬉しい”という感情。"
  },
  {
    "message": "私の中に、彼の感情が流れ込んできたと思った。"
  },
  {
    "message": "だと思ったが……。"
  },
  {
    "name": "伯奇",
    "message": "「っ」"
  },
  {
    "message": "心の奥底がちくりとした。"
  },
  {
    "name": "義貞",
    "message": "「どうされましたか？」"
  },
  {
    "name": "伯奇",
    "message": "「胸がちくりと致しました」"
  },
  {
    "name": "義貞",
    "message": "「ああ、それですか？　それでしたら、私などはいつもです」"
  },
  {
    "name": "伯奇",
    "message": "「いつも？」"
  },
  {
    "name": "義貞",
    "message": "「私は貴方の事を考えるといつも胸がちくりと痛みます」"
  },
  {
    "name": "伯奇",
    "message": "「私の事を考えると……」"
  },
  {
    "name": "義貞",
    "message": "「はい、私は貴方の事をお慕いしております故」"
  },
  {
    "message": "義貞殿が笑う。"
  },
  {
    "name": "伯奇",
    "message": "「っっ」"
  },
  {
    "message": "痛い。"
  },
  {
    "message": "胸が締め付けられる様に痛い。"
  },
  {
    "message": "何故だろう。"
  },
  {
    "message": "私の身体はどこかおかしくなってしまったのだろうか？"
  },
  {
    "name": "義貞",
    "message": "「どうしましたか？」"
  },
  {
    "name": "伯奇",
    "message": "「っ」"
  },
  {
    "message": "義貞様と目が合う。\r\n私は思わず目を伏せてしまう。"
  },
  {
    "message": "何故？"
  },
  {
    "message": "まったく理解出来ない。"
  },
  {
    "message": "本当に私はどうしてしまったのだろうか？"
  },
  {
    "name": "伯奇",
    "message": "「義貞様。私は……体調が悪い様です」"
  },
  {
    "name": "義貞",
    "message": "「体調が悪い？　それはいけないっ」"
  },
  {
    "message": "義貞様は私の腕を取る。"
  },
  {
    "name": "伯奇",
    "message": "「っっ！！」"
  },
  {
    "message": "目が合う。"
  },
  {
    "name": "伯奇",
    "message": "「あ、あうぅ……」"
  },
  {
    "name": "義貞",
    "message": "「たしかに顔が真っ赤です」"
  },
  {
    "name": "伯奇",
    "message": "「は、はい……」"
  },
  {
    "message": "これは、違う。"
  },
  {
    "message": "人の心が入ってきているのでは無い。"
  },
  {
    "message": "これは、私の中から生まれているもの。"
  },
  {
    "message": "これが感情？"
  },
  {
    "message": "私はいくつもの感情をのみ込んできた。"
  },
  {
    "name": "伯奇",
    "message": "「っっ」"
  },
  {
    "message": "ズキリと胸が痛む。"
  },
  {
    "name": "伯奇",
    "message": "「……っ」"
  },
  {
    "message": "自分の中に感情を見つけた瞬間、先ほどとは違う痛みに襲われる。"
  },
  {
    "name": "伯奇",
    "message": "「うっ……」"
  },
  {
    "message": "私はその場で崩れ落ちる。"
  },
  {
    "name": "義貞",
    "message": "「ど、どう致しましたか？」"
  },
  {
    "name": "伯奇",
    "message": "「わ、私は……」"
  },
  {
    "message": "義貞様が手をさしのべてくれた……、\r\nだけど私は、"
  },
  {
    "message": "たたきつける様にはねのける。"
  },
  {
    "name": "義貞",
    "message": "「は、伯奇殿……」"
  },
  {
    "name": "伯奇",
    "message": "「す、すみません。私は伯奇です」"
  },
  {
    "name": "義貞",
    "message": "「ああ、知っている。貴方は伯奇殿だ」"
  },
  {
    "name": "伯奇",
    "message": "「伯奇は器なり、人ならず」"
  },
  {
    "name": "伯奇",
    "message": "「故に、人の夢を喰う事が出来る」"
  },
  {
    "name": "義貞",
    "message": "「伯奇殿……」"
  },
  {
    "name": "伯奇",
    "message": "「っ」"
  },
  {
    "name": "伯奇",
    "message": "「申し訳ありません」"
  },
  {
    "message": "私は走り出す。"
  },
  {
    "message": "枯れ木の中をただひたすら走る。"
  },
  {
    "message": "彼から逃げるために、"
  },
  {
    "message": "ただこの枯れ木の森を走る。"
  },
  {
    "message": "空は湿気った空気が月をぼやかす。"
  },
  {
    "name": "里奈",
    "message": "「……」"
  },
  {
    "name": "優美",
    "message": "「里奈、どうしたの？」"
  },
  {
    "name": "里奈",
    "message": "「え？　何が？」"
  },
  {
    "name": "優美",
    "message": "「ずっと筆止まってた。考え事？」"
  },
  {
    "name": "里奈",
    "message": "「あ、そ、そうだね……」"
  },
  {
    "name": "優美",
    "message": "「も、もしかして、里奈は今夢の事を……」"
  },
  {
    "names": [
      "直哉",
      "？？？"
    ],
    "message": "「おー」"
  },
  {
    "name": "直哉",
    "message": "「二人ともやっぱり屋上にいるんだなぁ」"
  },
  {
    "name": "優美",
    "message": "「……」"
  },
  {
    "name": "直哉",
    "message": "「なんて目で俺を見ている……怖いぞ」"
  },
  {
    "name": "優美",
    "message": "「たぶん、そのままの表情だと思います」"
  },
  {
    "name": "里奈",
    "message": "「草薙先輩、どうされたのですか？　稟先輩に教えているのでは？」"
  },
  {
    "name": "直哉",
    "message": "「教えてるよ。だから連れてきた」"
  },
  {
    "name": "稟",
    "message": "「こんにちわー。二人とも」"
  },
  {
    "name": "優美",
    "message": "「稟先輩！」"
  },
  {
    "name": "里奈",
    "message": "「稟先輩も風景画描かれるのですか？」"
  },
  {
    "name": "稟",
    "message": "「うん、そうみたいだね」"
  },
  {
    "name": "直哉",
    "message": "「みんな、ムーア展に備えてそれぞれ作品やってるから、美術室誰もいないんだよ。辛気くさいし、外で描いてみるかって言ったら、稟がいいですねって」"
  },
  {
    "name": "優美",
    "message": "「稟先輩はウェルカムなのですが……なんで草薙先輩まで……」"
  },
  {
    "name": "直哉",
    "message": "「俺が教えてるんだから、しょうがないだろ」"
  },
  {
    "name": "稟",
    "message": "「優美ちゃんも草薙くんに教えてもらおうよ」"
  },
  {
    "name": "優美",
    "message": "「う゛……稟先輩に言われると……」"
  },
  {
    "name": "里奈",
    "message": "「稟先輩はどんな絵描かれるのですか？」"
  },
  {
    "name": "稟",
    "message": "「どうだろ。結構、あの教会の絵描いてみたいかも」"
  },
  {
    "name": "里奈",
    "message": "「教会？　『櫻達の足跡』の教会ですか」"
  },
  {
    "name": "稟",
    "message": "「うん、今年の夏のみんなの思い出だからね。絵にしてみたいかなぁ」"
  },
  {
    "name": "直哉",
    "message": "「ゴシック建築は構造がごちゃごちゃしてて難しいぞ。あれ、全部意味があってごちゃごちゃしてるんだから、適当には描けない」"
  },
  {
    "name": "稟",
    "message": "「その辺りは草薙くんが教えてくださいな」"
  },
  {
    "name": "稟",
    "message": "「それで？　それで？　里奈ちゃんと優美ちゃんどんな絵を描いてるのかな？」"
  },
  {
    "name": "里奈",
    "message": "「あ、ただの風景画ですよ……」"
  },
  {
    "name": "稟",
    "message": "「そうなんだ。ここからの風景は最高だからね」"
  },
  {
    "name": "里奈",
    "message": "「はい」"
  },
  {
    "name": "稟",
    "message": "「優美ちゃんは？」"
  },
  {
    "name": "優美",
    "message": "「稟先輩のヌードです！」"
  },
  {
    "name": "稟",
    "message": "「へ？」"
  },
  {
    "name": "優美",
    "message": "「いつか約束したではないですか！」"
  },
  {
    "name": "稟",
    "message": "「や、約束したっけ？」"
  },
  {
    "name": "里奈",
    "message": "「しとらんわ！」"
  },
  {
    "name": "里奈",
    "message": "「だいたい、あんたは稟先輩が来る前からずっとここで風景画描いてただろ！」"
  },
  {
    "name": "優美",
    "message": "「草薙先輩、ちょっといいですか？」"
  },
  {
    "name": "直哉",
    "message": "「なんだ？　何でそこで俺なんだ？」"
  },
  {
    "name": "優美",
    "message": "「目つぶし！」"
  },
  {
    "name": "直哉",
    "message": "「ぎゃぁぁぁぁぁぁぁぁぁぁぁぁあああ！」"
  },
  {
    "name": "稟",
    "message": "「く、草薙くん！」"
  },
  {
    "name": "優美",
    "message": "「大丈夫です。峰打ちですから」"
  },
  {
    "name": "里奈",
    "message": "「目つぶしに峰打ちは無いって……」"
  },
  {
    "name": "優美",
    "message": "「とりあえず、これをご覧ください」"
  },
  {
    "name": "稟",
    "message": "「え？」"
  },
  {
    "name": "里奈",
    "message": "「なんだこれ？」"
  },
  {
    "name": "優美",
    "message": "「稟先輩のヌード（想像図）です！」"
  },
  {
    "name": "稟",
    "message": "「って、これすごい上手いよ。まるで写真みたいだよ！」"
  },
  {
    "name": "里奈",
    "message": "「おまえなぁ。いつ盗撮したんだ？」"
  },
  {
    "name": "優美",
    "message": "「あはは、さすが里奈、バレたか」"
  },
  {
    "name": "里奈",
    "message": "「これアイコラですよ……」"
  },
  {
    "name": "稟",
    "message": "「アイコラ？」"
  },
  {
    "name": "里奈",
    "message": "「パソコンで顔と身体をコラージュさせるんですよ。主にアイドル写真をヌードにした事からアイコラと言われてます」"
  },
  {
    "name": "稟",
    "message": "「んじゃ、これ写真をコラージュさせたものなんだ。うまいもんだねぇ」"
  },
  {
    "name": "里奈",
    "message": "「稟先輩、何を悠長な事を、こいつ盗撮してたんですよ。もっと怒りましょうよ」"
  },
  {
    "name": "優美",
    "message": "「ごめん、里奈怒ってる？　浮気したかも！\r\nで、でも主に里奈の盗撮がほとんどだから、ゆるして！」"
  },
  {
    "name": "里奈",
    "message": "「そんな事を怒っているわけではない！　というか私がほとんどって何！？」"
  },
  {
    "name": "稟",
    "message": "「まぁ、まぁ、でも盗撮はいただけないなぁ。ちゃんと言ってくれれば、写真ぐらい一緒に撮るよ」"
  },
  {
    "name": "優美",
    "message": "「マジですか？　だったらダブルピースでとりあえず一枚！」"
  },
  {
    "name": "稟",
    "message": "「ダブルピース？　こ、こうかな？」"
  },
  {
    "name": "里奈",
    "message": "「やらなくていいです！　こいつ不純なものにしか使いませんから！！」"
  },
  {
    "name": "優美",
    "message": "「不純なものなんかに使ってません！　抱き枕とか作っているだけです！」"
  },
  {
    "name": "里奈",
    "message": "「つーか、写真で抱き枕作ってるのか！」"
  },
  {
    "name": "優美",
    "message": "「うん、里奈のだけで10種類ぐらいあるよ」"
  },
  {
    "name": "里奈",
    "message": "「いや、あるよ。じゃなくてだね……」"
  },
  {
    "name": "稟",
    "message": "「すごいね。里奈ちゃん愛されてるね」"
  },
  {
    "name": "優美",
    "message": "「はい！」"
  },
  {
    "name": "里奈",
    "message": "「いや、これは肯定しちゃいけない愛され方ですよ？\r\n盗撮されて、抱き枕ですよ」"
  },
  {
    "name": "稟",
    "message": "「そうだね。だから、もう盗撮はダメだよ」"
  },
  {
    "name": "優美",
    "message": "「はい！　では里奈もダブルピースで！」"
  },
  {
    "name": "里奈",
    "message": "「するかぁ！！」"
  },
  {
    "name": "稟",
    "message": "「でも、抱き枕とか可愛いよね。それ抱いて寝るのでしょ？」"
  },
  {
    "name": "優美",
    "message": "「はい、抱いて、寝ます。オナニーもします」"
  },
  {
    "name": "稟",
    "message": "「え？　お、オナニー？」"
  },
  {
    "name": "優美",
    "message": "「はい！」"
  },
  {
    "name": "里奈",
    "message": "「何、爽やかに、稟先輩にデタラメな事言ってるんだよー！\r\n稟先輩みたいな清純派な人にいぃ！」"
  },
  {
    "name": "稟",
    "message": "「そうなんだ。で、でも私もそれ大好きだから、大丈夫だよ」"
  },
  {
    "name": "里奈",
    "message": "「変な肯定入った！\r\nって、それフォローですよね。優美が恥ずかしくない様に」"
  },
  {
    "name": "稟",
    "message": "「ど、どうかなぁ？　結構昔っからエッチな本買ったりしてるから……」"
  },
  {
    "name": "優美",
    "message": "「マジですか？　稟先輩のオナニーってどんな感じなのですか？」"
  },
  {
    "name": "稟",
    "message": "「え？　わ、私の？　え、えっと……」"
  },
  {
    "name": "直哉",
    "message": "「目つぶしされてても、耳は聞こえるからな……」"
  },
  {
    "name": "優美",
    "message": "「先輩耳を貸してください」"
  },
  {
    "name": "直哉",
    "message": "「いいや！　今度は断る！」"
  },
  {
    "name": "優美",
    "message": "「ええい、このじゃますけがっ」"
  },
  {
    "name": "直哉",
    "message": "「なんだよ。お前らエロ話したいのなら、俺が席を外すよ。\r\nそんな事でいちいち鼓膜破られてたらたまらんわ」"
  },
  {
    "name": "稟",
    "message": "「え？　べ、別にエッチな話したいわけじゃないよ」"
  },
  {
    "name": "優美",
    "message": "「私はしたいです！」"
  },
  {
    "name": "里奈",
    "message": "「お前だけだ！」"
  },
  {
    "name": "優美",
    "message": "「たった一人だとしても、それを楽しみにしている人がいるのなら、全力で作品に打ち込む、それがクリエーターじゃない！」"
  },
  {
    "name": "里奈",
    "message": "「エロ話は作品ではない！」"
  },
  {
    "name": "優美",
    "message": "「いや、稟先輩のオナニーなら、それは作品と言って良いだろう」"
  },
  {
    "name": "里奈",
    "message": "「稟先輩も迷惑な話だよ」"
  },
  {
    "name": "稟",
    "message": "「どうだろ、それ言ったら優美ちゃんのオナニーの方が作品って言っていいんじゃないかな？　優美ちゃん可愛いし」"
  },
  {
    "name": "里奈",
    "message": "「変な返しが入った！」"
  },
  {
    "name": "優美",
    "message": "「では、真ん中をとって、里奈のオナニーが一番作品になるという事で」"
  },
  {
    "name": "直哉",
    "message": "「んで、それが結論でいいのか？」"
  },
  {
    "name": "里奈",
    "message": "「違います！　というか草薙先輩も涼しい顔で、こんな話聞かないでくださいっっ」"
  },
  {
    "name": "直哉",
    "message": "「だ、だったらどんな顔すればいいんだよ」"
  },
  {
    "name": "優美",
    "message": "「クール系の草薙先輩は表情を読みづらいので、めんどくさいから、ち○ちん勃ったら、以後挙手してください」"
  },
  {
    "name": "直哉",
    "message": "「挙手！」"
  },
  {
    "name": "優美",
    "message": "「早っ」"
  },
  {
    "name": "里奈",
    "message": "「っ、そ、そうなんですか？」"
  },
  {
    "name": "稟",
    "message": "「ぜ、全然そんな感じしなかった……」"
  },
  {
    "name": "直哉",
    "message": "「そりゃ、稟や氷川や川内野の口から、そのなんだ？　お、オナニーなんて言葉が出て、その姿を想像したら、そうにもなるだろ……」"
  },
  {
    "name": "里奈",
    "message": "「その姿を……」"
  },
  {
    "name": "稟",
    "message": "「そ、想像！？」"
  },
  {
    "name": "優美",
    "message": "「てやぁ！」"
  },
  {
    "name": "直哉",
    "message": "「ふんっ」"
  },
  {
    "name": "優美",
    "message": "「くっ」"
  },
  {
    "name": "直哉",
    "message": "「ふふふ、攻撃してくるのは分かっていたさ。俺もバカじゃない。\r\nどうせ、稟先輩や里奈のオナニー姿を想像するなぁ！　とか言って攻撃してくるなんざお見通しだ」"
  },
  {
    "name": "優美",
    "message": "「わ、私のだってダメ！」"
  },
  {
    "name": "直哉",
    "message": "「そうなのか？　川内野はそういうの気にしないと思ってた」"
  },
  {
    "name": "里奈",
    "message": "「それは、偏見ですよ。先輩」"
  },
  {
    "name": "稟",
    "message": "「そうですよ。優美ちゃんだって女の子なんですから、その発言は無神経すぎますよ」"
  },
  {
    "name": "直哉",
    "message": "「え？　俺？　今、俺が悪いの？」"
  },
  {
    "name": "優美",
    "message": "「と、とりあえず、そういうのを想像するのは卑怯です！」"
  },
  {
    "name": "直哉",
    "message": "「と言われても、そんな話をされたら、こっちも、男だし……」"
  },
  {
    "name": "優美",
    "message": "「くっ、これだから男は……」"
  },
  {
    "name": "直哉",
    "message": "「なんだよ。お前は想像しなかったのかよ！」"
  },
  {
    "name": "優美",
    "message": "「私はしたさ！」"
  },
  {
    "name": "直哉",
    "message": "「したのかよ！」"
  },
  {
    "name": "優美",
    "message": "「そりゃ、私はヘンタイですから、そのぐらいします。\r\nでも、男は無条件にその様な事をします！　だからダメだ！」"
  },
  {
    "name": "直哉",
    "message": "「デタラメな反論だな……」"
  },
  {
    "name": "里奈",
    "message": "「とりあえず、そろそろこのお話やめませんか？」"
  },
  {
    "name": "稟",
    "message": "「うん、どっちにしても、ちょっと男の人の前でする話じゃないよね」"
  },
  {
    "name": "優美",
    "message": "「くそ、このじゃますけがっ。せっかくのガールズエロトークが、お前のせいで！」"
  },
  {
    "name": "里奈",
    "message": "「いやいや、元々、あんまりこういう話はするもんじゃないよ。\r\n女の子同士でも」"
  },
  {
    "name": "稟",
    "message": "「そうかな？　私はこういうお話を女の子同士でするの好きだよ」"
  },
  {
    "name": "里奈",
    "message": "「え？　そ、そうなんですか？」"
  },
  {
    "name": "優美",
    "message": "「さすがは稟先輩」"
  },
  {
    "name": "直哉",
    "message": "「稟の言う事を真に受けるなよ。こいつは昔っから、空気読んで発言するからな」"
  },
  {
    "name": "稟",
    "message": "「そんな事ないよ。それも偏見だよ」"
  },
  {
    "name": "里奈",
    "message": "「いや、そこは、さすがに草薙先輩の言う方に乗っておきましょうよ……」"
  },
  {
    "name": "稟",
    "message": "「と、いいますか、全然、絵進んでませんよね」"
  },
  {
    "name": "里奈",
    "message": "「あ……」"
  },
  {
    "name": "直哉",
    "message": "「そりゃ、そうだろ……」"
  },
  {
    "name": "優美",
    "message": "「このじゃますけがっ」"
  },
  {
    "name": "直哉",
    "message": "「俺のせいかよ！」"
  }
]