[
  {
    "name": "稟",
    "message": "「すみません。冷凍食品になってしまって」"
  },
  {
    "name": "直哉",
    "message": "「いや、料理してもらえるだけ助かるよ。そもそも腹減ったって急かしたの俺だし」"
  },
  {
    "name": "稟",
    "message": "「それは私もですよ。性欲も高まっていたのですが、お腹もかなり減っていました」"
  },
  {
    "name": "直哉",
    "message": "「朝食から結構時間経っているし」"
  },
  {
    "name": "稟",
    "message": "「本当なら病院からの帰りにどこかで食事するぐらいの時間だったのですが、急いで帰ってきましたからねぇ」"
  },
  {
    "name": "直哉",
    "message": "「とは言っても、まだ全然、性欲も収まっていないんだけど」"
  },
  {
    "name": "稟",
    "message": "「そうですねぇ、ずっとなおくん勃ちっぱなしですねぇ。\r\nけど、ご飯の時ぐらい勃起禁止にしませんか？」"
  },
  {
    "name": "直哉",
    "message": "「禁止されても勃起はするよ。そもそも全然射精し足りないし」"
  },
  {
    "name": "稟",
    "message": "「そんな勃起してると……私が気になって食事どころじゃなくなるのですが……」"
  },
  {
    "name": "直哉",
    "message": "「まぁ、気にしないでくれ。すぐにでも俺は出来るという事だけだから」"
  },
  {
    "name": "稟",
    "message": "「なんですか……それ」"
  },
  {
    "name": "直哉",
    "message": "「まぁ、稟がよければ、飯食い終わったらという感じ……」"
  },
  {
    "name": "稟",
    "message": "「私がダメなわけないじゃないですか」"
  },
  {
    "name": "稟",
    "message": "「すぐにご飯済ませましょう……」"
  },
  {
    "name": "直哉",
    "message": "「り、稟の口気持ちいいぃ……」"
  },
  {
    "name": "稟",
    "message": "「ぢゅぷ……れろ……さっき、ちゅっ、ぢゅる、はぁはぁ、ずっと、なおくんの、お○んちん、舐めたかった……れす……ちゅっ……れろれろ……はむぅ、ぢゅゅる――、ぢゅるるる――」"
  },
  {
    "name": "直哉",
    "message": "「そうだな……ずっと、手コキ……だけだったし……」"
  },
  {
    "name": "稟",
    "message": "「はい、ちゅう……ぢゅる、ちゅむ……ずっと、射精介助、だけ、ちゅ、れろ、れしたぁ……ぢゅる、ちゅる……れろれろ……」"
  },
  {
    "name": "直哉",
    "message": "「あ゛、もうダメ、もう、イくっ……、もう出る……」"
  },
  {
    "name": "稟",
    "message": "「はぁはぁ、沢山、れろれろ……ぢゅるるる――せいえき……、くださいぃ。口？　顔？　胸？　髪の毛？　どこですかぁ……どこに出しても、かならず、全部、舐めとりますから……ぢゅるるる」"
  },
  {
    "name": "直哉",
    "message": "「全部にかけたい……」"
  },
  {
    "name": "稟",
    "message": "「それじゃ……レロレロ……わたしの、全身に、せいえきを、ぶっかけてください。全部、指ですくい取って、舐めて……飲みますから……」"
  },
  {
    "name": "直哉",
    "message": "「あ゛、あ゛、あ゛、あ゛、あ゛、だめ、だめだめだめ――稟っ、おれ、い、イぐッッッっっ――」"
  },
  {
    "name": "稟",
    "message": "「ずごいぃぃ……止まらないぃぃぃ、こし、ガクガクがとまらなぃんですぅぅぅ……これすごいぃぃぃ……」"
  },
  {
    "name": "直哉",
    "message": "「そ、そんな、足で、俺の腰を絡みつくと、そんな力強く、だいしゅきぃホールドされると……ち○こ、奥しか、届かないぃ……んがぁ！」"
  },
  {
    "name": "稟",
    "message": "「奥がいい。奥がいいのぉ。だからとめられない。だいしゅきななおくんを足から逃すとか…わたしにできらい、もっともっと、おま○この奥、ズボズボしてぼしぃ…なおくんのおち○ぽで、おま○この奥をズボズボしてほぢぃですぅ」"
  },
  {
    "name": "稟",
    "message": "「もっど、もっと、おま○こにビューしてほしいれす。せいえき、おま○こにびゅーしてぇぇ、おまん○からあふれるぐらい、びゅーしてもらうまで、わたひぃ、なおくんのち○ぽ、はなさないからぁ……」"
  },
  {
    "name": "直哉",
    "message": "「おれは、いくらでも……出るぞ……ずっと、今日まで、がまん、していたんだ……から……稟とのせっくす……」"
  },
  {
    "name": "稟",
    "message": "「ん゛ごぉぉ！？　お゛お゛いいよぉ、なおくんの、まだ、かたいぃぃ……ずぼ、ずぼ、おま○こから、音がするよぉ……なおくんの、せいえきが、おち○ぽでおま○このなかで、かきまわされてぇぇ……」"
  },
  {
    "name": "直哉",
    "message": "「あ゛、あ゛、あ゛、イ、イくぅ……だめだ……稟、ナカで……出す……」"
  },
  {
    "name": "稟",
    "message": "「ぎてぎてくださいぃぃぃ、なおくんのせいえき、わたしにくださいぃぃ。おま○この奥にせいえきビューしてぇぇぇ」"
  },
  {
    "message": "ドぴゅッ、どぴゅる、ドピュ、ドピュル、どぷっ――。"
  },
  {
    "name": "稟",
    "message": "「あ゛、ずごい……でてる、なおくんの、お○んちん、びゅっ、びゅっ、せいえき、わたしに、だしてくれてるッッッっっ――」"
  },
  {
    "name": "稟",
    "message": "「すごい、それすごぃぃぃ、お゛ふっ！？　おっ…ふっ！？　ふぁぁあ゛！？　\r\n……そ、それやばい……ヤバイやばいヤバイですぅぅぅ……なおくんの体重がぜんぶのって、わたしのおま○このおぐにぃぃぃぃい！？」"
  },
  {
    "name": "稟",
    "message": "「それいい。ぞれイイでしゅう……、なおくん、ぜんぶ体重かけて……そのまま、おち○ぽ、おしこんでぇぇ……ん゛ごぉぉ！？　あ、それ、それイイよぉ！？」"
  },
  {
    "name": "稟",
    "message": "「奥にいれたまま、いれたまま、おち○ぽのさき、さきが、奥で……、小刻みに、動いてるの……それ、すきです。それほんとうにきもちぃぃ……おほっ、おほっ、んほぉ！？　……んほぉおお？！」"
  },
  {
    "name": "稟",
    "message": "「らめぇ、らめぇ、なおぐんん――わたぢぃぃ、もう、らめぇ、あ゛、あ゛あ゛ぁイッグぅぅぅゥゥゥゥううううう――」"
  },
  {
    "name": "稟",
    "message": "「んきゃ、あぐっうっ、なか、でてる。せいえき、なおくんのぉ、また、でてるぅ、だいしゅき、だいしゅき、ぢゅる、ちゅ、れろれろ――むちゅっううう」"
  },
  {
    "name": "稟",
    "message": "「だいしゅきだいしゅき、ずっとなおくんとつながっていたいよぉ、ずっと、なおくんのお○んちん入れて生活したい……ぢゅるぅ、なおくんだいしゅき、なおくんのおち○ぽだいしゅきぃだよぉぉ――」"
  },
  {
    "name": "稟",
    "message": "「あれから……ずっと、セックスしてばかりだったね……」"
  },
  {
    "name": "直哉",
    "message": "「ああ、温泉行くとか話してたのに」"
  },
  {
    "name": "稟",
    "message": "「それは、明日から行くんです！」"
  },
  {
    "name": "直哉",
    "message": "「本当に？　もう結構な遅い時間だよ？」"
  },
  {
    "name": "稟",
    "message": "「うん、なんか電気も点けないでずっとセックスしてたら、\r\n普通に日が変わってました」"
  },
  {
    "name": "直哉",
    "message": "「電気点けたら、結構外から部屋の中が見えるよ？」"
  },
  {
    "name": "稟",
    "message": "「カーテンしてくださいよ」"
  },
  {
    "name": "直哉",
    "message": "「あそこのガラスドアはカーテンない」"
  },
  {
    "name": "稟",
    "message": "「なんですか？　そのフラグ？　外から見える様にセックスするんですか？」"
  },
  {
    "name": "直哉",
    "message": "「いや、そんな事させないよ……俺だけの稟を他に見られたくないし」"
  },
  {
    "name": "稟",
    "message": "「くすくす、ホントかなぁ……賢者タイムで言ってませんか？」"
  },
  {
    "name": "直哉",
    "message": "「まぁ、そうだけど……」"
  },
  {
    "name": "稟",
    "message": "「――ん？」"
  },
  {
    "name": "稟",
    "message": "「なんだろ――」"
  },
  {
    "name": "直哉",
    "message": "「どうした？」"
  },
  {
    "name": "稟",
    "message": "「なんか……」"
  },
  {
    "name": "稟",
    "message": "「鳴き声しません？」"
  },
  {
    "name": "直哉",
    "message": "「鳴き声？」"
  },
  {
    "name": "稟",
    "message": "「はい……なんだろ……遠くで、鳥が鳴いた様な……」"
  },
  {
    "name": "直哉",
    "message": "「夜って鳥、あんま鳴かないんじゃない？」"
  },
  {
    "name": "稟",
    "message": "「そうですよね……」"
  },
  {
    "message": "たしかに、鳥の美しい声が聞こえた様な気がした……。"
  },
  {
    "message": "だけれども、それは一回限りの声だったので、幻であった様な気がしてくる。"
  },
  {
    "message": "なおくんも聞いてないと言ってるし……。"
  },
  {
    "name": "稟",
    "message": "「けど……」"
  },
  {
    "name": "直哉",
    "message": "「けど？」"
  },
  {
    "name": "稟",
    "message": "「あ、いや何でもありません……」"
  },
  {
    "name": "稟",
    "message": "「明日は、ちゃんと起きて、旅行の準備しましょうね。明日なら間に合いますよ一泊ぐらい――」"
  },
  {
    "name": "直哉",
    "message": "「そうだな……」"
  },
  {
    "name": "直哉",
    "message": "「稟とこんな一緒にいるのなんて、久しぶりだったけど……やはり、ほとんどそれは介護だったし……」"
  },
  {
    "name": "直哉",
    "message": "「落ち着いて、二人でゆっくりという感じではなかった……」"
  },
  {
    "name": "直哉",
    "message": "「旅行もいいかもしれないな……」"
  },
  {
    "name": "直哉",
    "message": "「まぁ、おれは、家で、こうやってイチャイチャしてるだけでもいいんだけどさ……」"
  },
  {
    "name": "稟",
    "message": "「……――」"
  },
  {
    "name": "直哉",
    "message": "「ん？」"
  },
  {
    "name": "稟",
    "message": "「――………すー」"
  },
  {
    "name": "直哉",
    "message": "「もう寝たのか……。まぁ、寝るわな」"
  },
  {
    "name": "直哉",
    "message": "「風呂は明日だ……。俺も疲れたし、このまま寝る……」"
  },
  {
    "name": "稟",
    "message": "「ち○ぽ、なおくんのち○ぽ。、きもちいぃ……んぁぁあぁんっっ。ち○ぽ、きもちいい…………ち○ぽうれしいぃ、ち○ぽうれしいぃ、しゅきぃ、なおくんのおち○ぽだいしゅきぃぃぃ――」"
  },
  {
    "name": "直哉",
    "message": "「はぁ、はぁ、りん、りん、すげぇ、りんのま○こ、しめつけっ……んぐっ」"
  },
  {
    "name": "稟",
    "message": "「あ゛あ゛あ゛っっ、はうっ？！　んふぁ！？　らめぇ、おま○こ気持ち良すぎて、足、ガクガクしすぎて、たって、らんないよぉ……」"
  },
  {
    "name": "直哉",
    "message": "「はぁはぁ、大丈夫、全然、俺の力で、稟を、支えられるから……そのまま、ただ、きもちよくなって」"
  },
  {
    "name": "稟",
    "message": "「あ゛あ゛あ゛、もう、あしで立てない、だてないよぉ……おま○こきもちよすぎ、ほんとうに立てないよ？　んぁ！？」"
  },
  {
    "name": "稟",
    "message": "「バックすごいぃ、なおくんのバックすごいぃ、ちから、すごいから、からだごと、オナホみたいに……ぜんごしてぇ……あ゛あ゛あ゛っ……ずごいぃぃ……あんっ……奥までおち○ぽ届くぅぅ……」"
  },
  {
    "name": "稟",
    "message": "「すごいぃぃ、すごいよぉ……なおくんの、わんりょくで、からだぜんぶ、動かされて……あ゛……あ゛あ゛あ゛……すごいぃぃ、なおくんのでつらぬかれるぅぅ――」"
  },
  {
    "name": "稟",
    "message": "「あ゛ぁあああ……ずごい、ずごいよぉ……\r\nなおくんの、ち○ぽに、ズボズボ、つらぬかれてる……、\r\nすごいぃ……こんな事できるとか、なおくん、すごすぎるぅぅ……」"
  },
  {
    "name": "稟",
    "message": "「あ゛？　あ゛？　このバック、やば、これ、ヤバい、やつ……これ、もだめぇでしゅう……ん゛あ゛っ！？　こ、これ……やばいのくる……きちゃうっ」"
  },
  {
    "name": "稟",
    "message": "「らめらめらめぇ……くる……きちゃぅう……らめぇ……イク……おま○こガチイキしちゃうますぅ……ずごい、なおくんのち○ぽすごすぎてぇ」"
  },
  {
    "name": "稟",
    "message": "「らめぇ、こんなイキかた、した、こと、ないから……こわいぃ、いやぁ、らめぇ、これほんとうに、すごいのきそう……こわい、あ゛らめ………………」"
  },
  {
    "name": "稟",
    "message": "「イグ…………イグ…………んぁぁあぁん゛、イっぐぅぅぅぅぅぅぅ――ッッッっっ」"
  },
  {
    "name": "稟",
    "message": "「また冷凍食品になってしまいました……申し訳ございません」"
  },
  {
    "name": "直哉",
    "message": "「いや、そもそもセックスはじめたの二人でだし」"
  },
  {
    "name": "稟",
    "message": "「まぁ、二人でしか出来ませんからね……はぁ、今からだと、温泉行けないよなぁ」"
  },
  {
    "name": "直哉",
    "message": "「え？　もしかして諦めてなかったの？」"
  },
  {
    "name": "稟",
    "message": "「気持ちだけ……もちろん、薄々、無理だとは思ってました。昨晩も遅くまで起きてましたし……」"
  },
  {
    "name": "直哉",
    "message": "「うん、もう昼過ぎてるし」"
  },
  {
    "name": "稟",
    "message": "「不覚です……」"
  },
  {
    "name": "直哉",
    "message": "「まぁ、温泉はまた今度でいいじゃない」"
  },
  {
    "name": "稟",
    "message": "「その今度が、いつになるやら……」"
  },
  {
    "name": "直哉",
    "message": "「やっぱり、これだけ長期休暇取るとしわ寄せがある？」"
  },
  {
    "name": "稟",
    "message": "「まぁ言ってしまえば、そうですね……今年度の有休はすべて消化しきってます……」"
  },
  {
    "name": "直哉",
    "message": "「そ、そっか……」"
  },
  {
    "name": "直哉",
    "message": "「けどさ、そしたら、今後は、俺がアメリカに行くよ」"
  },
  {
    "name": "稟",
    "message": "「ボストンの物価は結構高いですよ……」"
  },
  {
    "name": "直哉",
    "message": "「そこはどうにかするし」"
  },
  {
    "name": "稟",
    "message": "「でもなおくんも会社ずっと休んでいるのですよね」"
  },
  {
    "name": "直哉",
    "message": "「それは、まぁ、そうなんだけど、一応は通勤中の事故だしさ」"
  },
  {
    "name": "稟",
    "message": "「労災保険使うと評価下がるとか聞きますが……」"
  },
  {
    "name": "直哉",
    "message": "「中小企業の評価はなんでも下がるし、なんならなんでも上がるから大丈夫」"
  },
  {
    "name": "稟",
    "message": "「全く分からない理屈です……」"
  },
  {
    "name": "直哉",
    "message": "「まぁさ。それはそれ、これはこれでさ。今日は、家でゆっくり二人で過ごそうよ」"
  },
  {
    "name": "稟",
    "message": "「家でゆっくりですか……、こんな二人がゆっくりなんて過ごしますかねぇ」"
  },
  {
    "name": "直哉",
    "message": "「それも含めてゆっくり……」"
  },
  {
    "name": "稟",
    "message": "「まぁ、それはそれで、というかむしろ、そっちの方がうれしい自分が悔しいわけですけど……」"
  },
  {
    "name": "稟",
    "message": "「温泉旅行よりも、なおくんとずっと家で裸でイチャイチャしつづけている方がうれしいとか…………」"
  },
  {
    "name": "直哉",
    "message": "「いいじゃん」"
  },
  {
    "name": "稟",
    "message": "「まぁ、いいんですけど……家から出ないで温泉旅行したいです」"
  },
  {
    "name": "稟",
    "message": "「突然、ここに温泉が出現しないかなぁ……」"
  },
  {
    "name": "直哉",
    "message": "「いや、普通にそれ、ウチのマンション倒壊するわ。温泉湧き出てるんだから……」"
  },
  {
    "name": "稟",
    "message": "「な、なんで……私は……自分のおもちゃでオナニーさせられているのでしょう」"
  },
  {
    "name": "直哉",
    "message": "「だって、これだけあるのなら、使っているの見てみたいじゃない？\r\n当たり前では？」"
  },
  {
    "name": "稟",
    "message": "「まぁ、いいのですけど……んっ、これは、クリトリスを包む様な構造をしてまして……この様に当てて……電源を入れると……んくっっ？！」"
  },
  {
    "name": "直哉",
    "message": "「あ、知っている。エロVTuberが使ってたヤツだ」"
  },
  {
    "name": "稟",
    "message": "「はぁ？　なんですか？　そのエロVTuberって？」"
  },
  {
    "name": "直哉",
    "message": "「あ、いや、なんでもありません」"
  },
  {
    "name": "稟",
    "message": "「なんでもないじゃないです！　なんですか！　それ！　誰なんですか？」"
  },
  {
    "name": "直哉",
    "message": "「いや、誰とか行っても、バーチャルなネット上の存在なんで――」"
  },
  {
    "name": "稟",
    "message": "「ちょっと調べます！」"
  },
  {
    "name": "直哉",
    "message": "「あ、待って、待ってくださいっ」"
  },
  {
    "name": "稟",
    "message": "「らめぇ……もう、こんな、ごまかし方ぁ……んぁッッッっっ――んきゃぁぁっっ？！」"
  },
  {
    "name": "稟",
    "message": "「なんでも、えっちしちゃえば、ゆるしてもらえるとか……ないん……です…よ？　んきゅ、あ゛あ゛、らめぇ、きもちいいよぉ……そこぉ……あんっ……それいいですぅ」"
  },
  {
    "name": "稟",
    "message": "「はっぁ、はっぁ、はうっ、らめぇ、きもちよくて、じぶんからこしをふっちゃう……なんで、わたし、なおくん、問いつめてた、のにぃぃ……んくっ」"
  },
  {
    "name": "稟",
    "message": "「でも、しょうが、ないですよね、んくっ、こ、こんな、なおくんのち○ぽ、きもちいいんだから、ごまかされても……んきゅ、……ぅん゛っ、んっはぁ……すごい……やっぱり、なおくんのお○んちんきもちいぃぃ――」"
  },
  {
    "name": "稟",
    "message": "「だめですぅ。こんな場所でぇ……、外から丸見えになるって、なおくん言ってたし……んきゃぁ、らめぇ、おち○こバックからいれられると――ん゛ごぉぉ！？」"
  },
  {
    "name": "稟",
    "message": "「だめ、もう、すぐに足がガタガタになって……あー……おま○こからガクガクするの……全身に伝わって……とまんない、とまんないよぉ……だめですぅ……きもちよすぎてぇぇ――」"
  },
  {
    "name": "稟",
    "message": "「あ゛、またキた。なおくんの腕力で、からだ全部、うごかされる……んあ゛っこれ……すごいぃ……あ゛ぁああ゛、さっきより、お○んちん、おっきくなってる……すごいぃ……おま○こきもちよくて、どんどん広がっちゃうっ……」"
  },
  {
    "name": "稟",
    "message": "「はひぃ！？　…………らめですぅぅんぁぁああっッッンっ！！　んきゃぁ、あ゛？　あ゛あ゛っっ――ぁぁああっッッ！？　あぁぁァァァァァァァ……ぁ、ぁ、ぁ、ァァァァァァァ……ぁ」"
  },
  {
    "name": "稟",
    "message": "「なおくんのお○んちん、なおくんのお○んちんっっ……きゃひぃんっッッ！！\r\nあ゛あ゛きもちよすぎるぅぅぅ…………も、もうらめぇです………これだめなヤツ……ですぅぅ――」"
  },
  {
    "name": "稟",
    "message": "「らめぇ、らめだよぉ。もう、なんかいも、イってるのにぃ……ぜ、ぜんぜん……我慢できないよぉぉ…………らめぇ、らめぇ、もう、だめですぅぅ……」"
  },
  {
    "name": "稟",
    "message": "「あ゛、ごめんなさい、わたしぃ、たえられないぃっッッ……ィイく……イクイクっ……イきますぅ！　イっちゃう！　イっちゃいますぅぅぅ――ッッッっ」"
  },
  {
    "name": "稟",
    "message": "「んぐっっ――はひぃんっッッ！！」"
  }
]